Workbook
Name ConstGrowth: DCF!$C$28
Name DiscountRate: DCF!$C$31
Name ExitMultiple: DCF!$C$32
Name GrowthMode: DCF!$C$27
Name MarginEnd: DCF!$C$30
Name MarginStart: DCF!$C$29
Name NetAdj: DCF!$C$33
Name Price: DCF!$C$25
Name PriceDate: DCF!$C$34
Name Shares: DCF!$C$26
Name StubFraction: DCF!$C$35
Name ValuePerShare: DCF!$C$66

Sheet DCF
B2: Titan Company Ltd (NSE: TITAN): DCF Valuation
B3: Prepared by Daksh Chaudhary · 26-Sep-2026 · Base case, via Net Income · ₹ bn unless stated
B5: DCF ASSUMPTIONS
B6: Revenue Growth | C6: =(AC41/M41)^(1/AC40)-1 -> 0.12604317
B7: Net Margin | C7: =TEXT(MarginStart,"0.0%")&" → "&TEXT(MarginEnd,"0.0%") -> 6.7% → 6.6%
B8: Forecast Period | C8: =(AC40-1)&" years" -> 15 years
B10: MODEL SETTINGS
B11: Template | C11: via Net Income
B12: Discount Rate | C12: =DiscountRate -> 0.1026
B13: Exit Multiple | C13: =ExitMultiple -> 26.522648
B15: VALUATION RESULT
B16: DCF VALUE PER SHARE
B17: =ValuePerShare -> 4052.2133 | C17: =C69 -> Overvaluation 17%
B18: ="vs. market price "&TEXT(Price,"#,##0")&" INR · DCF value is "&TEXT(ABS(C68),"0.0%")&IF(C68<0," below"," above")&" the price" -> vs. market price 4,884 INR · DCF value is 17.0% below the price
B20: Blue = input | Black = formula | Green = link to Data sheet
B24: 1 INPUTS & ASSUMPTIONS
B25: Current share price (₹) | C25: 4884 | D25: Last close as of 25-Sep-2026 (NSE: TITAN)
B26: Diluted shares outstanding (mn) | C26: 890 | D26: Diluted share count (basic ≈ 887.8 mn)
B27: Revenue growth mode | C27: Base case (per year) | D27: Base case = per-year path in row 43; Constant CAGR = C28 in every year
B28: Constant revenue growth (CAGR mode only) | C28: 0.126 | D28: Used only in Constant CAGR mode
B29: Net margin, start (fade anchor) | C29: 0.067105625 | D29: Fades along an S-curve to the FY2042 margin
B30: Net margin, end (FY2042) | C30: 0.06628 | D30: Long-term net margin
B31: Discount rate (cost of equity) | C31: 0.1026 | D31: Required return on equity
B32: Exit multiple (P/E on FY2042 net income) | C32: 26.522648 | D32: Terminal P/E applied to FY2042 net income
B33: Net adjustments / equity bridge (₹ bn) | C33: 0 | D33: Cash / debt adjustments (none applied)
B34: Price date (valuation date) | C34: =DATE(2026,9,25) -> 46290 | D34: NSE close used for the price in C25; the stub runs from here to 31-Mar-2027
B35: Share of FY2027 still ahead (stub) | C35: =(DATE(2027,3,31)-C34)/365 -> 0.51232877 | D35: Share of FY2027 net income still ahead of the price date; discount periods = stub, stub + 1, … years
B37: 2 FORECAST (₹ bn; fiscal years end 31 March)
B38: Fiscal year | C38: Unit | D38: 2017 | E38: 2018 | F38: 2019 | G38: 2020 | H38: 2021 | I38: 2022 | J38: 2023 | K38: 2024 | L38: 2025 | M38: 2026 | N38: 2027 | O38: 2028 | P38: 2029 | Q38: 2030 | R38: 2031 | S38: 2032 | T38: 2033 | U38: 2034 | V38: 2035 | W38: 2036 | X38: 2037 | Y38: 2038 | Z38: 2039 | AA38: 2040 | AB38: 2041 | AC38: 2042
B39: Period | D39: Actual | E39: Actual | F39: Actual | G39: Actual | H39: Actual | I39: Actual | J39: Actual | K39: Actual | L39: Actual | M39: Actual | N39: Forecast | O39: Forecast | P39: Forecast | Q39: Forecast | R39: Forecast | S39: Forecast | T39: Forecast | U39: Forecast | V39: Forecast | W39: Forecast | X39: Forecast | Y39: Forecast | Z39: Forecast | AA39: Forecast | AB39: Forecast | AC39: Forecast
B40: Forecast year (t) | N40: 1 | O40: =N40+1 -> 2 | P40: =O40+1 -> 3 | Q40: =P40+1 -> 4 | R40: =Q40+1 -> 5 | S40: =R40+1 -> 6 | T40: =S40+1 -> 7 | U40: =T40+1 -> 8 | V40: =U40+1 -> 9 | ... AC40: =AB40+1 -> 16
B41: Revenue | C41: ₹ bn | D41: =Data!C7/100 -> 133.821 | E41: =Data!C8/100 -> 161.56 | F41: =Data!C9/100 -> 197.785 | G41: =Data!C10/100 -> 210.515 | H41: =Data!C11/100 -> 216.44 | I41: =Data!C12/100 -> 287.99 | J41: =Data!C13/100 -> 405.75 | K41: =Data!C14/100 -> 510.84 | L41: =Data!C15/100 -> 604.56 | M41: =Data!C16/100 -> 875.84 | N41: =M41*(1+N42) -> 1026.4285 | O41: =N41*(1+O42) -> 1207.1746 | P41: =O41*(1+P42) -> 1412.8551 | Q41: =P41*(1+Q42) -> 1651.18 | R41: =Q41*(1+R42) -> 1921.8977 | S41: =R41*(1+S42) -> 2223.1469 | T41: =S41*(1+T42) -> 2551.3032 | U41: =T41*(1+U42) -> 2901.0733 | ... AC41: =AB41*(1+AC42) -> 5852.0147
B42: Revenue growth | C42: % | E42: =IF(D41=0,0,E41/D41-1) -> 0.20728436 | F42: =IF(E41=0,0,F41/E41-1) -> 0.2242201 | G42: =IF(F41=0,0,G41/F41-1) -> 0.064362818 | H42: =IF(G41=0,0,H41/G41-1) -> 0.028145263 | I42: =IF(H41=0,0,I41/H41-1) -> 0.3305766 | J42: =IF(I41=0,0,J41/I41-1) -> 0.40890309 | K42: =IF(J41=0,0,K41/J41-1) -> 0.25900185 | L42: =IF(K41=0,0,L41/K41-1) -> 0.18346253 | M42: =IF(L41=0,0,M41/L41-1) -> 0.44872304 | N42: =IF(GrowthMode="Constant CAGR",ConstGrowth,N43) -> 0.1719361 | O42: =IF(GrowthMode="Constant CAGR",ConstGrowth,O43) -> 0.1760922 | P42: =IF(GrowthMode="Constant CAGR",ConstGrowth,P43) -> 0.17038176 | Q42: =IF(GrowthMode="Constant CAGR",ConstGrowth,Q43) -> 0.1686832 | R42: =IF(GrowthMode="Constant CAGR",ConstGrowth,R43) -> 0.16395411 | S42: =IF(GrowthMode="Constant CAGR",ConstGrowth,S43) -> 0.15674569 | T42: =IF(GrowthMode="Constant CAGR",ConstGrowth,T43) -> 0.14760889 | U42: =IF(GrowthMode="Constant CAGR",ConstGrowth,U43) -> 0.1370947 | ... AC42: =IF(GrowthMode="Constant CAGR",ConstGrowth,AC43) -> 0.06951
B43: Revenue growth, base case (input) | C43: % input | N43: 0.1719361 | O43: 0.1760922 | P43: 0.17038176 | Q43: 0.1686832 | R43: 0.16395411 | S43: 0.15674569 | T43: 0.14760889 | U43: 0.1370947 | V43: 0.12575406 | W43: 0.11413794 | X43: 0.1027973 | Y43: 0.092283105 | Z43: 0.083146315 | AA43: 0.075937893 | AB43: 0.0712088 | AC43: 0.06951
B44: Net margin | C44: % | D44: =IF(D41=0,0,D46/D41) -> 0.053168038 | E44: =IF(E41=0,0,E46/E41) -> 0.069949245 | F44: =IF(F41=0,0,F46/F41) -> 0.070996284 | G44: =IF(G41=0,0,G46/G41) -> 0.071320333 | H44: =IF(H41=0,0,H46/H41) -> 0.044954722 | I44: =IF(I41=0,0,I46/I41) -> 0.075454009 | J44: =IF(J41=0,0,J46/J41) -> 0.080098583 | K44: =IF(K41=0,0,K46/K41) -> 0.068436301 | ... M44: =IF(M41=0,0,M46/M41) -> 0.057921538 | N44: =MarginStart+(MarginEnd-MarginStart)*N45 -> 0.067096353 | O44: =MarginStart+(MarginEnd-MarginStart)*O45 -> 0.067070149 | P44: =MarginStart+(MarginEnd-MarginStart)*P45 -> 0.067029432 | Q44: =MarginStart+(MarginEnd-MarginStart)*Q45 -> 0.066976621 | R44: =MarginStart+(MarginEnd-MarginStart)*R45 -> 0.066914135 | S44: =MarginStart+(MarginEnd-MarginStart)*S45 -> 0.066844392 | T44: =MarginStart+(MarginEnd-MarginStart)*T45 -> 0.066769812 | U44: =MarginStart+(MarginEnd-MarginStart)*U45 -> 0.066692813 | ... AC44: =MarginStart+(MarginEnd-MarginStart)*AC45 -> 0.06628
B45: Margin fade weight (S-curve, 0 → 1) | C45: weight | N45: =3*(N$40/$AC$40)^2-2*(N$40/$AC$40)^3 -> 0.011230469 | O45: =3*(O$40/$AC$40)^2-2*(O$40/$AC$40)^3 -> 0.04296875 | P45: =3*(P$40/$AC$40)^2-2*(P$40/$AC$40)^3 -> 0.092285156 | Q45: =3*(Q$40/$AC$40)^2-2*(Q$40/$AC$40)^3 -> 0.15625 | R45: =3*(R$40/$AC$40)^2-2*(R$40/$AC$40)^3 -> 0.23193359 | S45: =3*(S$40/$AC$40)^2-2*(S$40/$AC$40)^3 -> 0.31640625 | T45: =3*(T$40/$AC$40)^2-2*(T$40/$AC$40)^3 -> 0.40673828 | U45: =3*(U$40/$AC$40)^2-2*(U$40/$AC$40)^3 -> 0.5 | ... AC45: =3*(AC$40/$AC$40)^2-2*(AC$40/$AC$40)^3 -> 1
B46: Net income | C46: ₹ bn | D46: =Data!D7/100 -> 7.115 | E46: =Data!D8/100 -> 11.301 | F46: =Data!D9/100 -> 14.042 | G46: =Data!D10/100 -> 15.014 | H46: =Data!D11/100 -> 9.73 | I46: =Data!D12/100 -> 21.73 | J46: =Data!D13/100 -> 32.5 | K46: =Data!D14/100 -> 34.96 | L46: =Data!D15/100 -> 33.37 | M46: =Data!D16/100 -> 50.73 | N46: =N41*N44 -> 68.86961 | O46: =O41*O44 -> 80.965378 | P46: =P41*P44 -> 94.702874 | Q46: =Q41*Q44 -> 110.59046 | R46: =R41*R44 -> 128.60212 | S46: =S41*S44 -> 148.6049 | T46: =T41*T44 -> 170.35003 | U46: =U41*U44 -> 193.48074 | ... AC46: =AC41*AC44 -> 387.87154
B47: Net income growth | C47: % | E47: =IF(D46=0,0,E46/D46-1) -> 0.5883345 | F47: =IF(E46=0,0,F46/E46-1) -> 0.24254491 | G47: =IF(F46=0,0,G46/F46-1) -> 0.069220909 | H47: =IF(G46=0,0,H46/G46-1) -> -0.35193819 | I47: =IF(H46=0,0,I46/H46-1) -> 1.2332991 | J47: =IF(I46=0,0,J46/I46-1) -> 0.49562816 | K47: =IF(J46=0,0,K46/J46-1) -> 0.075692308 | L47: =IF(K46=0,0,L46/K46-1) -> -0.045480549 | ... AC47: =IF(AB46=0,0,AC46/AB46-1) -> 0.069360403
B49: 3 DISCOUNTING (cash flow to equity = net income)
B50: Share of fiscal year counted | C50: share | N50: =IF(N$40=1,StubFraction,1) -> 0.51232877 | O50: =IF(O$40=1,StubFraction,1) -> 1 | P50: =IF(P$40=1,StubFraction,1) -> 1 | Q50: =IF(Q$40=1,StubFraction,1) -> 1 | R50: =IF(R$40=1,StubFraction,1) -> 1 | S50: =IF(S$40=1,StubFraction,1) -> 1 | T50: =IF(T$40=1,StubFraction,1) -> 1 | U50: =IF(U$40=1,StubFraction,1) -> 1 | ... AC50: =IF(AC$40=1,StubFraction,1) -> 1
B51: Cash flow to equity (net income × share) | C51: ₹ bn | N51: =N46*N50 -> 35.283882 | O51: =O46*O50 -> 80.965378 | P51: =P46*P50 -> 94.702874 | Q51: =Q46*Q50 -> 110.59046 | R51: =R46*R50 -> 128.60212 | S51: =S46*S50 -> 148.6049 | T51: =T46*T50 -> 170.35003 | U51: =U46*U50 -> 193.48074 | ... AC51: =AC46*AC50 -> 387.87154
B52: Discount period (years from valuation date) | C52: years | N52: =StubFraction+N$40-1 -> 0.51232877 | O52: =StubFraction+O$40-1 -> 1.5123288 | P52: =StubFraction+P$40-1 -> 2.5123288 | Q52: =StubFraction+Q$40-1 -> 3.5123288 | R52: =StubFraction+R$40-1 -> 4.5123288 | S52: =StubFraction+S$40-1 -> 5.5123288 | T52: =StubFraction+T$40-1 -> 6.5123288 | U52: =StubFraction+U$40-1 -> 7.5123288 | ... AC52: =StubFraction+AC$40-1 -> 15.512329
B53: Discount factor = 1 / (1 + r)^period | C53: factor | N53: =1/(1+DiscountRate)^N52 -> 0.95119168 | O53: =1/(1+DiscountRate)^O52 -> 0.86268065 | P53: =1/(1+DiscountRate)^P52 -> 0.78240581 | Q53: =1/(1+DiscountRate)^Q52 -> 0.70960077 | R53: =1/(1+DiscountRate)^R52 -> 0.64357045 | S53: =1/(1+DiscountRate)^S52 -> 0.58368442 | T53: =1/(1+DiscountRate)^T52 -> 0.52937096 | U53: =1/(1+DiscountRate)^U52 -> 0.48011152 | ... AC53: =1/(1+DiscountRate)^AC52 -> 0.21978509
B54: Present value | C54: ₹ bn | N54: =N51*N53 -> 33.561735 | O54: =O51*O53 -> 69.847264 | P54: =P51*P53 -> 74.096079 | Q54: =Q51*Q53 -> 78.475074 | R54: =R51*R53 -> 82.764527 | S54: =S51*S53 -> 86.738368 | T54: =T51*T53 -> 90.178361 | U54: =U51*U53 -> 92.892332 | ... AC54: =AC51*AC53 -> 85.24838
B56: 4 VALUATION
B57: PV of forecast cash flows (₹ bn) | C57: =SUM(N54:AC54) -> 1345.4571
B58: FY2042 net income (₹ bn) | C58: =AC46 -> 387.87154
B59: Exit multiple (P/E) | C59: =ExitMultiple -> 26.522648
B60: Terminal value at FY2042 (₹ bn) | C60: =C58*C59 -> 10287.38
B61: Discount factor for FY2042 | C61: =AC53 -> 0.21978509
B62: PV of terminal value (₹ bn) | C62: =C60*C61 -> 2261.0127
B63: Net adjustments / equity bridge (₹ bn) | C63: =NetAdj -> 0
B64: Equity value (₹ bn) | C64: =C57+C62+C63 -> 3606.4699
B65: Diluted shares (mn) | C65: =Shares -> 890
B66: DCF value per share (₹) | C66: =IF(C65=0,0,C64/C65*1000) -> 4052.2133
B67: Current share price (₹) | C67: =Price -> 4884
B68: DCF value vs price: upside / (downside) | C68: =IF(C67=0,0,C66/C67-1) -> -0.17030849
B69: Verdict | C69: =IF(C66<C67,"Overvaluation","Undervaluation")&" "&TEXT(ABS(C68),"0%") -> Overvaluation 17%
B70: Terminal value as % of equity value | C70: =IF(C64=0,0,C62/C64) -> 0.62693238
B74: 5 SENSITIVITY: DCF VALUE PER SHARE (₹)
B75: Discount rate (rows) × exit P/E (columns) | J75: Rate step | K75: 0.005
C76: r \ P/E → | D76: =ExitMultiple+(-2)*$K$76 -> 20.522648 | E76: =ExitMultiple+(-1)*$K$76 -> 23.522648 | F76: =ExitMultiple+(0)*$K$76 -> 26.522648 | G76: =ExitMultiple+(1)*$K$76 -> 29.522648 | H76: =ExitMultiple+(2)*$K$76 -> 32.522648 | J76: P/E step | K76: 3
C77: =DiscountRate+(-2)*$K$75 -> 0.0926 | D77: =IF(Shares=0,0,(SUMPRODUCT($N$51:$AC$51/(1+$C77)^$N$52:$AC$52)+$C$58*D$76/(1+$C77)^$AC$52+NetAdj)/Shares*1000) -> 3899.7512 | E77: =IF(Shares=0,0,(SUMPRODUCT($N$51:$AC$51/(1+$C77)^$N$52:$AC$52)+$C$58*E$76/(1+$C77)^$AC$52+NetAdj)/Shares*1000) -> 4230.7271 | F77: =IF(Shares=0,0,(SUMPRODUCT($N$51:$AC$51/(1+$C77)^$N$52:$AC$52)+$C$58*F$76/(1+$C77)^$AC$52+NetAdj)/Shares*1000) -> 4561.7031 | G77: =IF(Shares=0,0,(SUMPRODUCT($N$51:$AC$51/(1+$C77)^$N$52:$AC$52)+$C$58*G$76/(1+$C77)^$AC$52+NetAdj)/Shares*1000) -> 4892.679 | H77: =IF(Shares=0,0,(SUMPRODUCT($N$51:$AC$51/(1+$C77)^$N$52:$AC$52)+$C$58*H$76/(1+$C77)^$AC$52+NetAdj)/Shares*1000) -> 5223.655
C78: =DiscountRate+(-1)*$K$75 -> 0.0976 | D78: =IF(Shares=0,0,(SUMPRODUCT($N$51:$AC$51/(1+$C78)^$N$52:$AC$52)+$C$58*D$76/(1+$C78)^$AC$52+NetAdj)/Shares*1000) -> 3681.3548 | E78: =IF(Shares=0,0,(SUMPRODUCT($N$51:$AC$51/(1+$C78)^$N$52:$AC$52)+$C$58*E$76/(1+$C78)^$AC$52+NetAdj)/Shares*1000) -> 3989.6999 | F78: =IF(Shares=0,0,(SUMPRODUCT($N$51:$AC$51/(1+$C78)^$N$52:$AC$52)+$C$58*F$76/(1+$C78)^$AC$52+NetAdj)/Shares*1000) -> 4298.045 | G78: =IF(Shares=0,0,(SUMPRODUCT($N$51:$AC$51/(1+$C78)^$N$52:$AC$52)+$C$58*G$76/(1+$C78)^$AC$52+NetAdj)/Shares*1000) -> 4606.3901 | H78: =IF(Shares=0,0,(SUMPRODUCT($N$51:$AC$51/(1+$C78)^$N$52:$AC$52)+$C$58*H$76/(1+$C78)^$AC$52+NetAdj)/Shares*1000) -> 4914.7351
C79: =DiscountRate+(0)*$K$75 -> 0.1026 | D79: =IF(Shares=0,0,(SUMPRODUCT($N$51:$AC$51/(1+$C79)^$N$52:$AC$52)+$C$58*D$76/(1+$C79)^$AC$52+NetAdj)/Shares*1000) -> 3477.5052 | E79: =IF(Shares=0,0,(SUMPRODUCT($N$51:$AC$51/(1+$C79)^$N$52:$AC$52)+$C$58*E$76/(1+$C79)^$AC$52+NetAdj)/Shares*1000) -> 3764.8592 | F79: =IF(Shares=0,0,(SUMPRODUCT($N$51:$AC$51/(1+$C79)^$N$52:$AC$52)+$C$58*F$76/(1+$C79)^$AC$52+NetAdj)/Shares*1000) -> 4052.2133 | G79: =IF(Shares=0,0,(SUMPRODUCT($N$51:$AC$51/(1+$C79)^$N$52:$AC$52)+$C$58*G$76/(1+$C79)^$AC$52+NetAdj)/Shares*1000) -> 4339.5674 | H79: =IF(Shares=0,0,(SUMPRODUCT($N$51:$AC$51/(1+$C79)^$N$52:$AC$52)+$C$58*H$76/(1+$C79)^$AC$52+NetAdj)/Shares*1000) -> 4626.9215 | I79: → base case
C80: =DiscountRate+(1)*$K$75 -> 0.1076 | D80: =IF(Shares=0,0,(SUMPRODUCT($N$51:$AC$51/(1+$C80)^$N$52:$AC$52)+$C$58*D$76/(1+$C80)^$AC$52+NetAdj)/Shares*1000) -> 3287.1403 | E80: =IF(Shares=0,0,(SUMPRODUCT($N$51:$AC$51/(1+$C80)^$N$52:$AC$52)+$C$58*E$76/(1+$C80)^$AC$52+NetAdj)/Shares*1000) -> 3555.0178 | F80: =IF(Shares=0,0,(SUMPRODUCT($N$51:$AC$51/(1+$C80)^$N$52:$AC$52)+$C$58*F$76/(1+$C80)^$AC$52+NetAdj)/Shares*1000) -> 3822.8953 | G80: =IF(Shares=0,0,(SUMPRODUCT($N$51:$AC$51/(1+$C80)^$N$52:$AC$52)+$C$58*G$76/(1+$C80)^$AC$52+NetAdj)/Shares*1000) -> 4090.7729 | H80: =IF(Shares=0,0,(SUMPRODUCT($N$51:$AC$51/(1+$C80)^$N$52:$AC$52)+$C$58*H$76/(1+$C80)^$AC$52+NetAdj)/Shares*1000) -> 4358.6504
C81: =DiscountRate+(2)*$K$75 -> 0.1126 | D81: =IF(Shares=0,0,(SUMPRODUCT($N$51:$AC$51/(1+$C81)^$N$52:$AC$52)+$C$58*D$76/(1+$C81)^$AC$52+NetAdj)/Shares*1000) -> 3109.2813 | E81: =IF(Shares=0,0,(SUMPRODUCT($N$51:$AC$51/(1+$C81)^$N$52:$AC$52)+$C$58*E$76/(1+$C81)^$AC$52+NetAdj)/Shares*1000) -> 3359.0814 | F81: =IF(Shares=0,0,(SUMPRODUCT($N$51:$AC$51/(1+$C81)^$N$52:$AC$52)+$C$58*F$76/(1+$C81)^$AC$52+NetAdj)/Shares*1000) -> 3608.8814 | G81: =IF(Shares=0,0,(SUMPRODUCT($N$51:$AC$51/(1+$C81)^$N$52:$AC$52)+$C$58*G$76/(1+$C81)^$AC$52+NetAdj)/Shares*1000) -> 3858.6814 | H81: =IF(Shares=0,0,(SUMPRODUCT($N$51:$AC$51/(1+$C81)^$N$52:$AC$52)+$C$58*H$76/(1+$C81)^$AC$52+NetAdj)/Shares*1000) -> 4108.4815
B83: Revenue growth shift vs current path, every year (rows) × FY2042 net margin (columns) | J83: Growth step | K83: 0.02
C84: Δ growth \ margin → | D84: =MarginEnd+(-2)*$K$84 -> 0.05628 | E84: =MarginEnd+(-1)*$K$84 -> 0.06128 | F84: =MarginEnd+(0)*$K$84 -> 0.06628 | G84: =MarginEnd+(1)*$K$84 -> 0.07128 | H84: =MarginEnd+(2)*$K$84 -> 0.07628 | J84: Margin step | K84: 0.005
C85: =(-2)*$K$83 -> -0.04 | D85: =IF(Shares=0,0,(MarginStart*SUMPRODUCT($N$50:$AC$50,$N92:$AC92,$N$53:$AC$53)+(D$84-MarginStart)*SUMPRODUCT($N$50:$AC$50,$N92:$AC92,$N$45:$AC$45,$N$53:$AC$53)+$AC92*(MarginStart+(D$84-MarginStart)*$AC$45)*ExitMultiple*$AC$53+NetAdj)/Shares*1000) -> 2232.006 | E85: =IF(Shares=0,0,(MarginStart*SUMPRODUCT($N$50:$AC$50,$N92:$AC92,$N$53:$AC$53)+(E$84-MarginStart)*SUMPRODUCT($N$50:$AC$50,$N92:$AC92,$N$45:$AC$45,$N$53:$AC$53)+$AC92*(MarginStart+(E$84-MarginStart)*$AC$45)*ExitMultiple*$AC$53+NetAdj)/Shares*1000) -> 2382.8705 | F85: =IF(Shares=0,0,(MarginStart*SUMPRODUCT($N$50:$AC$50,$N92:$AC92,$N$53:$AC$53)+(F$84-MarginStart)*SUMPRODUCT($N$50:$AC$50,$N92:$AC92,$N$45:$AC$45,$N$53:$AC$53)+$AC92*(MarginStart+(F$84-MarginStart)*$AC$45)*ExitMultiple*$AC$53+NetAdj)/Shares*1000) -> 2533.7349 | G85: =IF(Shares=0,0,(MarginStart*SUMPRODUCT($N$50:$AC$50,$N92:$AC92,$N$53:$AC$53)+(G$84-MarginStart)*SUMPRODUCT($N$50:$AC$50,$N92:$AC92,$N$45:$AC$45,$N$53:$AC$53)+$AC92*(MarginStart+(G$84-MarginStart)*$AC$45)*ExitMultiple*$AC$53+NetAdj)/Shares*1000) -> 2684.5993 | H85: =IF(Shares=0,0,(MarginStart*SUMPRODUCT($N$50:$AC$50,$N92:$AC92,$N$53:$AC$53)+(H$84-MarginStart)*SUMPRODUCT($N$50:$AC$50,$N92:$AC92,$N$45:$AC$45,$N$53:$AC$53)+$AC92*(MarginStart+(H$84-MarginStart)*$AC$45)*ExitMultiple*$AC$53+NetAdj)/Shares*1000) -> 2835.4638
C86: =(-1)*$K$83 -> -0.02 | D86: =IF(Shares=0,0,(MarginStart*SUMPRODUCT($N$50:$AC$50,$N93:$AC93,$N$53:$AC$53)+(D$84-MarginStart)*SUMPRODUCT($N$50:$AC$50,$N93:$AC93,$N$45:$AC$45,$N$53:$AC$53)+$AC93*(MarginStart+(D$84-MarginStart)*$AC$45)*ExitMultiple*$AC$53+NetAdj)/Shares*1000) -> 2805.9511 | E86: =IF(Shares=0,0,(MarginStart*SUMPRODUCT($N$50:$AC$50,$N93:$AC93,$N$53:$AC$53)+(E$84-MarginStart)*SUMPRODUCT($N$50:$AC$50,$N93:$AC93,$N$45:$AC$45,$N$53:$AC$53)+$AC93*(MarginStart+(E$84-MarginStart)*$AC$45)*ExitMultiple*$AC$53+NetAdj)/Shares*1000) -> 3002.9702 | F86: =IF(Shares=0,0,(MarginStart*SUMPRODUCT($N$50:$AC$50,$N93:$AC93,$N$53:$AC$53)+(F$84-MarginStart)*SUMPRODUCT($N$50:$AC$50,$N93:$AC93,$N$45:$AC$45,$N$53:$AC$53)+$AC93*(MarginStart+(F$84-MarginStart)*$AC$45)*ExitMultiple*$AC$53+NetAdj)/Shares*1000) -> 3199.9893 | G86: =IF(Shares=0,0,(MarginStart*SUMPRODUCT($N$50:$AC$50,$N93:$AC93,$N$53:$AC$53)+(G$84-MarginStart)*SUMPRODUCT($N$50:$AC$50,$N93:$AC93,$N$45:$AC$45,$N$53:$AC$53)+$AC93*(MarginStart+(G$84-MarginStart)*$AC$45)*ExitMultiple*$AC$53+NetAdj)/Shares*1000) -> 3397.0084 | H86: =IF(Shares=0,0,(MarginStart*SUMPRODUCT($N$50:$AC$50,$N93:$AC93,$N$53:$AC$53)+(H$84-MarginStart)*SUMPRODUCT($N$50:$AC$50,$N93:$AC93,$N$45:$AC$45,$N$53:$AC$53)+$AC93*(MarginStart+(H$84-MarginStart)*$AC$45)*ExitMultiple*$AC$53+NetAdj)/Shares*1000) -> 3594.0276
C87: =(0)*$K$83 -> 0 | D87: =IF(Shares=0,0,(MarginStart*SUMPRODUCT($N$50:$AC$50,$N94:$AC94,$N$53:$AC$53)+(D$84-MarginStart)*SUMPRODUCT($N$50:$AC$50,$N94:$AC94,$N$45:$AC$45,$N$53:$AC$53)+$AC94*(MarginStart+(D$84-MarginStart)*$AC$45)*ExitMultiple*$AC$53+NetAdj)/Shares*1000) -> 3538.776 | E87: =IF(Shares=0,0,(MarginStart*SUMPRODUCT($N$50:$AC$50,$N94:$AC94,$N$53:$AC$53)+(E$84-MarginStart)*SUMPRODUCT($N$50:$AC$50,$N94:$AC94,$N$45:$AC$45,$N$53:$AC$53)+$AC94*(MarginStart+(E$84-MarginStart)*$AC$45)*ExitMultiple*$AC$53+NetAdj)/Shares*1000) -> 3795.4947 | F87: =IF(Shares=0,0,(MarginStart*SUMPRODUCT($N$50:$AC$50,$N94:$AC94,$N$53:$AC$53)+(F$84-MarginStart)*SUMPRODUCT($N$50:$AC$50,$N94:$AC94,$N$45:$AC$45,$N$53:$AC$53)+$AC94*(MarginStart+(F$84-MarginStart)*$AC$45)*ExitMultiple*$AC$53+NetAdj)/Shares*1000) -> 4052.2133 | G87: =IF(Shares=0,0,(MarginStart*SUMPRODUCT($N$50:$AC$50,$N94:$AC94,$N$53:$AC$53)+(G$84-MarginStart)*SUMPRODUCT($N$50:$AC$50,$N94:$AC94,$N$45:$AC$45,$N$53:$AC$53)+$AC94*(MarginStart+(G$84-MarginStart)*$AC$45)*ExitMultiple*$AC$53+NetAdj)/Shares*1000) -> 4308.932 | H87: =IF(Shares=0,0,(MarginStart*SUMPRODUCT($N$50:$AC$50,$N94:$AC94,$N$53:$AC$53)+(H$84-MarginStart)*SUMPRODUCT($N$50:$AC$50,$N94:$AC94,$N$45:$AC$45,$N$53:$AC$53)+$AC94*(MarginStart+(H$84-MarginStart)*$AC$45)*ExitMultiple*$AC$53+NetAdj)/Shares*1000) -> 4565.6506 | I87: → base case
C88: =(1)*$K$83 -> 0.02 | D88: =IF(Shares=0,0,(MarginStart*SUMPRODUCT($N$50:$AC$50,$N95:$AC95,$N$53:$AC$53)+(D$84-MarginStart)*SUMPRODUCT($N$50:$AC$50,$N95:$AC95,$N$45:$AC$45,$N$53:$AC$53)+$AC95*(MarginStart+(D$84-MarginStart)*$AC$45)*ExitMultiple*$AC$53+NetAdj)/Shares*1000) -> 4473.1746 | E88: =IF(Shares=0,0,(MarginStart*SUMPRODUCT($N$50:$AC$50,$N95:$AC95,$N$53:$AC$53)+(E$84-MarginStart)*SUMPRODUCT($N$50:$AC$50,$N95:$AC95,$N$45:$AC$45,$N$53:$AC$53)+$AC95*(MarginStart+(E$84-MarginStart)*$AC$45)*ExitMultiple*$AC$53+NetAdj)/Shares*1000) -> 4806.857 | F88: =IF(Shares=0,0,(MarginStart*SUMPRODUCT($N$50:$AC$50,$N95:$AC95,$N$53:$AC$53)+(F$84-MarginStart)*SUMPRODUCT($N$50:$AC$50,$N95:$AC95,$N$45:$AC$45,$N$53:$AC$53)+$AC95*(MarginStart+(F$84-MarginStart)*$AC$45)*ExitMultiple*$AC$53+NetAdj)/Shares*1000) -> 5140.5394 | G88: =IF(Shares=0,0,(MarginStart*SUMPRODUCT($N$50:$AC$50,$N95:$AC95,$N$53:$AC$53)+(G$84-MarginStart)*SUMPRODUCT($N$50:$AC$50,$N95:$AC95,$N$45:$AC$45,$N$53:$AC$53)+$AC95*(MarginStart+(G$84-MarginStart)*$AC$45)*ExitMultiple*$AC$53+NetAdj)/Shares*1000) -> 5474.2218 | H88: =IF(Shares=0,0,(MarginStart*SUMPRODUCT($N$50:$AC$50,$N95:$AC95,$N$53:$AC$53)+(H$84-MarginStart)*SUMPRODUCT($N$50:$AC$50,$N95:$AC95,$N$45:$AC$45,$N$53:$AC$53)+$AC95*(MarginStart+(H$84-MarginStart)*$AC$45)*ExitMultiple*$AC$53+NetAdj)/Shares*1000) -> 5807.9042
C89: =(2)*$K$83 -> 0.04 | D89: =IF(Shares=0,0,(MarginStart*SUMPRODUCT($N$50:$AC$50,$N96:$AC96,$N$53:$AC$53)+(D$84-MarginStart)*SUMPRODUCT($N$50:$AC$50,$N96:$AC96,$N$45:$AC$45,$N$53:$AC$53)+$AC96*(MarginStart+(D$84-MarginStart)*$AC$45)*ExitMultiple*$AC$53+NetAdj)/Shares*1000) -> 5662.5488 | E89: =IF(Shares=0,0,(MarginStart*SUMPRODUCT($N$50:$AC$50,$N96:$AC96,$N$53:$AC$53)+(E$84-MarginStart)*SUMPRODUCT($N$50:$AC$50,$N96:$AC96,$N$45:$AC$45,$N$53:$AC$53)+$AC96*(MarginStart+(E$84-MarginStart)*$AC$45)*ExitMultiple*$AC$53+NetAdj)/Shares*1000) -> 6095.1202 | F89: =IF(Shares=0,0,(MarginStart*SUMPRODUCT($N$50:$AC$50,$N96:$AC96,$N$53:$AC$53)+(F$84-MarginStart)*SUMPRODUCT($N$50:$AC$50,$N96:$AC96,$N$45:$AC$45,$N$53:$AC$53)+$AC96*(MarginStart+(F$84-MarginStart)*$AC$45)*ExitMultiple*$AC$53+NetAdj)/Shares*1000) -> 6527.6915 | G89: =IF(Shares=0,0,(MarginStart*SUMPRODUCT($N$50:$AC$50,$N96:$AC96,$N$53:$AC$53)+(G$84-MarginStart)*SUMPRODUCT($N$50:$AC$50,$N96:$AC96,$N$45:$AC$45,$N$53:$AC$53)+$AC96*(MarginStart+(G$84-MarginStart)*$AC$45)*ExitMultiple*$AC$53+NetAdj)/Shares*1000) -> 6960.2629 | H89: =IF(Shares=0,0,(MarginStart*SUMPRODUCT($N$50:$AC$50,$N96:$AC96,$N$53:$AC$53)+(H$84-MarginStart)*SUMPRODUCT($N$50:$AC$50,$N96:$AC96,$N$45:$AC$45,$N$53:$AC$53)+$AC96*(MarginStart+(H$84-MarginStart)*$AC$45)*ExitMultiple*$AC$53+NetAdj)/Shares*1000) -> 7392.8342
B91: Workings for the sensitivity table and chart
B92: ="Revenue path, growth shift "&TEXT(C85,"+0.0%;-0.0%;0.0%")&" (₹ bn)" -> Revenue path, growth shift -4.0% (₹ bn) | C92: =C85 -> -0.04 | N92: =$M$41*(1+N$42+$C92) -> 991.39491 | O92: =N92*(1+O$42+$C92) -> 1126.316 | P92: =O92*(1+P$42+$C92) -> 1273.1671 | Q92: =P92*(1+Q$42+$C92) -> 1437.0023 | R92: =Q92*(1+R$42+$C92) -> 1615.1246 | S92: =R92*(1+S$42+$C92) -> 1803.6835 | T92: =S92*(1+T$42+$C92) -> 1997.7758 | U92: =T92*(1+U$42+$C92) -> 2191.7493 | V92: =U92*(1+V$42+$C92) -> 2379.7007 | ... AC92: =AB92*(1+AC$42+$C92) -> 3279.6052
B93: ="Revenue path, growth shift "&TEXT(C86,"+0.0%;-0.0%;0.0%")&" (₹ bn)" -> Revenue path, growth shift -2.0% (₹ bn) | C93: =C86 -> -0.02 | N93: =$M$41*(1+N$42+$C93) -> 1008.9117 | O93: =N93*(1+O$42+$C93) -> 1166.395 | P93: =O93*(1+P$42+$C93) -> 1341.7995 | Q93: =P93*(1+Q$42+$C93) -> 1541.3025 | R93: =Q93*(1+R$42+$C93) -> 1763.1793 | S93: =R93*(1+S$42+$C93) -> 2004.2865 | T93: =S93*(1+T$42+$C93) -> 2260.0513 | U93: =T93*(1+U$42+$C93) -> 2524.6913 | V93: =U93*(1+V$42+$C93) -> 2791.6877 | ... AC93: =AB93*(1+AC$42+$C93) -> 4392.4064
B94: ="Revenue path, growth shift "&TEXT(C87,"+0.0%;-0.0%;0.0%")&" (₹ bn)" -> Revenue path, growth shift 0.0% (₹ bn) | C94: =C87 -> 0 | N94: =$M$41*(1+N$42+$C94) -> 1026.4285 | O94: =N94*(1+O$42+$C94) -> 1207.1746 | P94: =O94*(1+P$42+$C94) -> 1412.8551 | Q94: =P94*(1+Q$42+$C94) -> 1651.18 | R94: =Q94*(1+R$42+$C94) -> 1921.8977 | S94: =R94*(1+S$42+$C94) -> 2223.1469 | T94: =S94*(1+T$42+$C94) -> 2551.3032 | U94: =T94*(1+U$42+$C94) -> 2901.0733 | V94: =U94*(1+V$42+$C94) -> 3265.8951 | ... AC94: =AB94*(1+AC$42+$C94) -> 5852.0147
B95: ="Revenue path, growth shift "&TEXT(C88,"+0.0%;-0.0%;0.0%")&" (₹ bn)" -> Revenue path, growth shift +2.0% (₹ bn) | C95: =C88 -> 0.02 | N95: =$M$41*(1+N$42+$C95) -> 1043.9453 | O95: =N95*(1+O$42+$C95) -> 1248.6548 | P95: =O95*(1+P$42+$C95) -> 1486.3759 | Q95: =P95*(1+Q$42+$C95) -> 1766.8301 | R95: =Q95*(1+R$42+$C95) -> 2091.8458 | S95: =R95*(1+S$42+$C95) -> 2461.5705 | T95: =S95*(1+T$42+$C95) -> 2874.1516 | U95: =T95*(1+U$42+$C95) -> 3325.6656 | V95: =U95*(1+V$42+$C95) -> 3810.3948 | ... AC95: =AB95*(1+AC$42+$C95) -> 7757.302
B96: ="Revenue path, growth shift "&TEXT(C89,"+0.0%;-0.0%;0.0%")&" (₹ bn)" -> Revenue path, growth shift +4.0% (₹ bn) | C96: =C89 -> 0.04 | N96: =$M$41*(1+N$42+$C96) -> 1061.4621 | O96: =N96*(1+O$42+$C96) -> 1290.8358 | P96: =O96*(1+P$42+$C96) -> 1562.4041 | Q96: =P96*(1+Q$42+$C96) -> 1888.4516 | R96: =Q96*(1+R$42+$C96) -> 2273.609 | S96: =R96*(1+S$42+$C96) -> 2720.9318 | T96: =S96*(1+T$42+$C96) -> 3231.4028 | U96: =T96*(1+U$42+$C96) -> 3803.6671 | V96: =U96*(1+V$42+$C96) -> 4434.1404 | ... AC96: =AB96*(1+AC$42+$C96) -> 10232.804
B98: Chart: forecast shading (1 = forecast year) | D98: =IF(D$39="Forecast",1,0) -> 0 | E98: =IF(E$39="Forecast",1,0) -> 0 | F98: =IF(F$39="Forecast",1,0) -> 0 | G98: =IF(G$39="Forecast",1,0) -> 0 | H98: =IF(H$39="Forecast",1,0) -> 0 | I98: =IF(I$39="Forecast",1,0) -> 0 | J98: =IF(J$39="Forecast",1,0) -> 0 | K98: =IF(K$39="Forecast",1,0) -> 0 | ... AC98: =IF(AC$39="Forecast",1,0) -> 1
B99: Chart: revenue CAGR guide line (₹ bn) | D99: =IF(D$38=$M$38,$M$41,IF(D$38=$AC$38,$AC$41,IF(D$38=$U$38,($M$41+$AC$41)/2,NA()))) -> #N/A | E99: =IF(E$38=$M$38,$M$41,IF(E$38=$AC$38,$AC$41,IF(E$38=$U$38,($M$41+$AC$41)/2,NA()))) -> #N/A | F99: =IF(F$38=$M$38,$M$41,IF(F$38=$AC$38,$AC$41,IF(F$38=$U$38,($M$41+$AC$41)/2,NA()))) -> #N/A | G99: =IF(G$38=$M$38,$M$41,IF(G$38=$AC$38,$AC$41,IF(G$38=$U$38,($M$41+$AC$41)/2,NA()))) -> #N/A | H99: =IF(H$38=$M$38,$M$41,IF(H$38=$AC$38,$AC$41,IF(H$38=$U$38,($M$41+$AC$41)/2,NA()))) -> #N/A | I99: =IF(I$38=$M$38,$M$41,IF(I$38=$AC$38,$AC$41,IF(I$38=$U$38,($M$41+$AC$41)/2,NA()))) -> #N/A | J99: =IF(J$38=$M$38,$M$41,IF(J$38=$AC$38,$AC$41,IF(J$38=$U$38,($M$41+$AC$41)/2,NA()))) -> #N/A | K99: =IF(K$38=$M$38,$M$41,IF(K$38=$AC$38,$AC$41,IF(K$38=$U$38,($M$41+$AC$41)/2,NA()))) -> #N/A | ... AC99: =IF(AC$38=$M$38,$M$41,IF(AC$38=$AC$38,$AC$41,IF(AC$38=$U$38,($M$41+$AC$41)/2,NA()))) -> 5852.0147
B100: Chart: net income CAGR guide line (₹ bn) | D100: =IF(D$38=$M$38,$M$46,IF(D$38=$AC$38,$AC$46,IF(D$38=$U$38,($M$46+$AC$46)/2,NA()))) -> #N/A | E100: =IF(E$38=$M$38,$M$46,IF(E$38=$AC$38,$AC$46,IF(E$38=$U$38,($M$46+$AC$46)/2,NA()))) -> #N/A | F100: =IF(F$38=$M$38,$M$46,IF(F$38=$AC$38,$AC$46,IF(F$38=$U$38,($M$46+$AC$46)/2,NA()))) -> #N/A | G100: =IF(G$38=$M$38,$M$46,IF(G$38=$AC$38,$AC$46,IF(G$38=$U$38,($M$46+$AC$46)/2,NA()))) -> #N/A | H100: =IF(H$38=$M$38,$M$46,IF(H$38=$AC$38,$AC$46,IF(H$38=$U$38,($M$46+$AC$46)/2,NA()))) -> #N/A | I100: =IF(I$38=$M$38,$M$46,IF(I$38=$AC$38,$AC$46,IF(I$38=$U$38,($M$46+$AC$46)/2,NA()))) -> #N/A | J100: =IF(J$38=$M$38,$M$46,IF(J$38=$AC$38,$AC$46,IF(J$38=$U$38,($M$46+$AC$46)/2,NA()))) -> #N/A | K100: =IF(K$38=$M$38,$M$46,IF(K$38=$AC$38,$AC$46,IF(K$38=$U$38,($M$46+$AC$46)/2,NA()))) -> #N/A | ... AC100: =IF(AC$38=$M$38,$M$46,IF(AC$38=$AC$38,$AC$46,IF(AC$38=$U$38,($M$46+$AC$46)/2,NA()))) -> 387.87154
B101: Chart label: revenue CAGR | C101: =TEXT(C6,"0.0%")&" CAGR" -> 12.6% CAGR
B102: Chart label: net income CAGR | C102: =TEXT((AC46/M46)^(1/AC40)-1,"0.0%")&" CAGR" -> 13.6% CAGR
B103: Chart title | C103: =AC38&" · FORECAST" -> 2042 · FORECAST
B104: Chart legend: revenue | C104: ="Revenue "&TEXT(AC41/1000,"0.0")&"T" -> Revenue 5.9T
B105: Chart legend: net income | C105: ="Net Income "&TEXT(AC46,"0.0")&"B" -> Net Income 387.9B

Sheet Data
B2: Titan Company Ltd (NSE: TITAN): source data & notes
B3: Blue = hard-coded source data. ₹ crore; fiscal years end 31 March (2026 = Apr-2025 to Mar-2026).
B5: HISTORICAL FINANCIALS, CONSOLIDATED (₹ crore)
B6: Fiscal year | C6: Revenue | D6: Net income | E6: Net margin | F6: Revenue growth | G6: NI growth
B7: 2017 | C7: 13382.1 | D7: 711.5 | E7: =IF(C7=0,0,D7/C7) -> 0.053168038
B8: 2018 | C8: 16156 | D8: 1130.1 | E8: =IF(C8=0,0,D8/C8) -> 0.069949245 | F8: =IF(C7=0,0,C8/C7-1) -> 0.20728436 | G8: =IF(D7=0,0,D8/D7-1) -> 0.5883345
B9: 2019 | C9: 19778.5 | D9: 1404.2 | E9: =IF(C9=0,0,D9/C9) -> 0.070996284 | F9: =IF(C8=0,0,C9/C8-1) -> 0.2242201 | G9: =IF(D8=0,0,D9/D8-1) -> 0.24254491
B10: 2020 | C10: 21051.5 | D10: 1501.4 | E10: =IF(C10=0,0,D10/C10) -> 0.071320333 | F10: =IF(C9=0,0,C10/C9-1) -> 0.064362818 | G10: =IF(D9=0,0,D10/D9-1) -> 0.069220909
B11: 2021 | C11: 21644 | D11: 973 | E11: =IF(C11=0,0,D11/C11) -> 0.044954722 | F11: =IF(C10=0,0,C11/C10-1) -> 0.028145263 | G11: =IF(D10=0,0,D11/D10-1) -> -0.35193819
B12: 2022 | C12: 28799 | D12: 2173 | E12: =IF(C12=0,0,D12/C12) -> 0.075454009 | F12: =IF(C11=0,0,C12/C11-1) -> 0.3305766 | G12: =IF(D11=0,0,D12/D11-1) -> 1.2332991
B13: 2023 | C13: 40575 | D13: 3250 | E13: =IF(C13=0,0,D13/C13) -> 0.080098583 | F13: =IF(C12=0,0,C13/C12-1) -> 0.40890309 | G13: =IF(D12=0,0,D13/D12-1) -> 0.49562816
B14: 2024 | C14: 51084 | D14: 3496 | E14: =IF(C14=0,0,D14/C14) -> 0.068436301 | F14: =IF(C13=0,0,C14/C13-1) -> 0.25900185 | G14: =IF(D13=0,0,D14/D13-1) -> 0.075692308
B15: 2025 | C15: 60456 | D15: 3337 | E15: =IF(C15=0,0,D15/C15) -> 0.055197168 | F15: =IF(C14=0,0,C15/C14-1) -> 0.18346253 | G15: =IF(D14=0,0,D15/D14-1) -> -0.045480549
B16: 2026 | C16: 87584 | D16: 5073 | E16: =IF(C16=0,0,D16/C16) -> 0.057921538 | F16: =IF(C15=0,0,C16/C15-1) -> 0.44872304 | G16: =IF(D15=0,0,D16/D15-1) -> 0.52022775
B17: Source: company filings (consolidated), via Alpha Spread and Screener.in, retrieved 26-Sep-2026. Revenue = revenue from operations; net income = profit attributable to shareholders.
B19: LATEST REPORTED QUARTER (₹ crore)
B20: Quarter | C20: Revenue | D20: Net income | E20: Net margin
B21: Q1 FY2027 (Apr–Jun 2026) | C21: 21356 | D21: 1777 | E21: =IF(C21=0,0,D21/C21) -> 0.083208466
B22: Q1 FY2026 (Apr–Jun 2025) | C22: 16523 | D22: 1091 | E22: =IF(C22=0,0,D22/C22) -> 0.066029171
B23: Source: Screener.in quarterly results (consolidated). The FY2027 estimate includes this reported Q1; the model values the stock as of the price date (25-Sep-2026) and counts the remaining 51% of FY2027.
B25: METHODOLOGY
B26: 1. Net-income DCF: each year's net income is treated as the cash flow to equity. Equity value = PV of net income + PV of terminal value + net adjustments (none).
B27: 2. Revenue: FY2026 actual (₹875.8 bn) grows 17.2%, 17.6% and 17.0% in FY2027–FY2029 (analyst estimates), then fades on an S-curve from 17.04% to 6.95% by FY2042. The fade from FY2030 is my own assumption: it replaces the analysts' 7.2% estimate for FY2030. CAGR FY2026–FY2042: 12.6%.
B28: 3. Net margin: fades on an S-curve (weight 3x² – 2x³, x = t/16) from 6.71% to 6.63% by FY2042.
B29: 4. Timing: valuation date = price date (25-Sep-2026). The remaining 51% of FY2027 net income is counted; cash flows are discounted to each 31-March year-end (0.51, 1.51, … years).
B30: 5. Discount rate: 10.26% cost of equity. Explicit forecast: FY2028–FY2042 (15 years) plus the FY2027 stub.
B31: 6. Terminal value: FY2042 net income × 26.52x exit P/E, discounted with the FY2042 factor.
B32: 7. Value per share: equity value / 890 mn diluted shares = ₹4,052.21, 17.0% below the ₹4,884 market price (NSE close, 25-Sep-2026).
B35: SOURCES
B36: Alpha Spread: TITAN DCF base case (forecast assumptions to FY2029, cost of equity, exit multiple), retrieved 26-Sep-2026
B37: Screener.in: Titan Company consolidated financials
... B39: For education and analysis only; not investment advice.
