Workbook
Name ConstGrowth: Valuation!$C$28
Name DiscountRate: Valuation!$C$31
Name ExitMultiple: Valuation!$C$32
Name FcffValuePerShare: 'FCFF DCF'!$C$84
Name GrowthMode: Valuation!$C$27
Name MarginEnd: Valuation!$C$30
Name MarginStart: Valuation!$C$29
Name NetAdj: Valuation!$C$33
Name Price: Valuation!$C$25
Name PriceDate: Valuation!$C$34
Name Shares: Valuation!$C$26
Name StubFraction: Valuation!$C$35
Name ValuePerShare: Valuation!$C$66

Sheet FCFF DCF
B2: Titan Company Ltd (NSE: TITAN): Free Cash Flow (FCFF) DCF
B3: Prepared by Daksh Chaudhary · 4-Oct-2026 · ₹ crore unless stated · same revenue path, price date and cost of equity as the Valuation sheet · Blue = input
B5: 1 INPUTS
B6: Share price (₹) | C6: =Price -> 4515.7 | D6: Linked to the Valuation sheet
B7: Price date | C7: =PriceDate -> 46296 | D7: NSE close; the stub runs from here to 31-Mar-2027
B8: Diluted shares (mn) | C8: =Shares -> 890
B9: Tax rate | C9: 0.2517 | D9: Indian corporate rate under the new regime (25.17%)
B10: Cost of equity | C10: =DiscountRate -> 0.1026 | D10: Linked to the Valuation sheet
B11: Gold on loan treated as | C11: Operating | D11: Operating (base) or Debt
B12: Gold-loan fee if operating (my assumption) | C12: 0.02 | D12: Yearly cost, deducted from EBIT
B13: EBIT margin, before gold-loan fee | C13: =AVERAGE(E37:I37) -> 0.09451628 | D13: FY2022-FY2026 average
B14: D&A, % of sales | C14: =AVERAGE(E40:I40) -> 0.011409878 | D14: FY2022-FY2026 average
B15: Capex, % of sales | C15: =AVERAGE(E39:I39) -> 0.024809174 | D15: FY2022-FY2026 average
B16: Working capital, % of sales | C16: =IF($C$11="Debt",AVERAGE(G42:I42),AVERAGE(G44:I44)) -> 0.23829195 | D16: FY2024-FY2026 average (the years with a gold-on-loan split)
B17: Terminal growth | C17: 0.06 | D17: Nominal, in rupees, after FY2042
B18: WACC override (blank = computed) | D18: Used by the sensitivity table
B19: Share of FY2027 still ahead (stub) | C19: =StubFraction -> 0.49589041
B21: 2 HISTORY (consolidated, ₹ crore; Screener.in, gold on loan from ICICI Direct's Q4FY26 update)
B22: Fiscal year | D22: 2021 | E22: 2022 | F22: 2023 | G22: 2024 | H22: 2025 | I22: 2026
B23: Sales | D23: 21644 | E23: 28799 | F23: 40575 | G23: 51084 | H23: 60456 | I23: 87584
B24: Profit before tax | D24: 1327 | E24: 2904 | F24: 4447 | G24: 4623 | H24: 4535 | I24: 6801
B25: Interest | D25: 203 | E25: 218 | F25: 300 | G25: 619 | H25: 953 | I25: 1180
B26: Other income | D26: 180 | E26: 177 | F26: 306 | G26: 534 | H26: 487 | I26: 450
B27: Depreciation | D27: 375 | E27: 399 | F27: 441 | G27: 584 | H27: 693 | I27: 826
B28: Net block | D28: 2523 | E28: 2544 | F28: 2998 | G28: 3709 | H28: 4062 | I28: 6878
B29: Capital work in progress | D29: 32 | E29: 85 | F29: 144 | G29: 97 | H29: 105 | I29: 163
B30: Other assets (incl. inventory, receivables, cash) | D30: 11065 | E30: 18265 | F30: 21363 | G30: 25396 | H30: 34490 | I30: 50014
B31: Other liabilities | D31: 3309 | E31: 4610 | F31: 5802 | G31: 6626 | H31: 8244 | I31: 14237
B32: Cash & bank | D32: 560 | E32: 1573 | F32: 1343 | G32: 1526 | H32: 1584 | I32: 1917
B33: Borrowings (incl. gold on loan and leases) | D33: 5638 | E33: 7275 | F33: 9367 | G33: 15528 | H33: 20777 | I33: 30621
B34: Gold on loan | G34: 5341 | H34: 7810 | I34: 16070
B36: EBIT = PBT + interest − other income | D36: =D24+D25-D26 -> 1350 | E36: =E24+E25-E26 -> 2945 | F36: =F24+F25-F26 -> 4441 | G36: =G24+G25-G26 -> 4708 | H36: =H24+H25-H26 -> 5001 | I36: =I24+I25-I26 -> 7531
B37: EBIT margin | D37: =D36/D23 -> 0.062372944 | E37: =E36/E23 -> 0.1022605 | F37: =F36/F23 -> 0.10945163 | G37: =G36/G23 -> 0.092161929 | H37: =H36/H23 -> 0.082721318 | I37: =I36/I23 -> 0.085986025
B38: Capex = Δ net block + Δ CWIP + depreciation | E38: =E28-D28+E29-D29+E27 -> 473 | F38: =F28-E28+F29-E29+F27 -> 954 | G38: =G28-F28+G29-F29+G27 -> 1248 | H38: =H28-G28+H29-G29+H27 -> 1054 | I38: =I28-H28+I29-H29+I27 -> 3700
B39: Capex, % of sales | E39: =E38/E23 -> 0.016424181 | F39: =F38/F23 -> 0.023512015 | G39: =G38/G23 -> 0.02443035 | H39: =H38/H23 -> 0.017434167 | I39: =I38/I23 -> 0.042245159
B40: D&A, % of sales | D40: =D27/D23 -> 0.017325818 | E40: =E27/E23 -> 0.013854648 | F40: =F27/F23 -> 0.010868762 | G40: =G27/G23 -> 0.011432151 | H40: =H27/H23 -> 0.011462882 | I40: =I27/I23 -> 0.0094309463
B41: Working capital, gold on loan as debt = other assets − cash − other liabilities | D41: =D30-D32-D31 -> 7196 | E41: =E30-E32-E31 -> 12082 | F41: =F30-F32-F31 -> 14218 | G41: =G30-G32-G31 -> 17244 | H41: =H30-H32-H31 -> 24662 | I41: =I30-I32-I31 -> 33860
B42: % of sales | D42: =D41/D23 -> 0.33247089 | E42: =E41/E23 -> 0.41952846 | F42: =F41/F23 -> 0.35041282 | G42: =G41/G23 -> 0.33756166 | H42: =H41/H23 -> 0.40793304 | I42: =I41/I23 -> 0.38660029
B43: Working capital, gold on loan as operating = above − gold on loan | G43: =G41-G34 -> 11903 | H43: =H41-H34 -> 16852 | I43: =I41-I34 -> 17790
B44: % of sales | G44: =G43/G23 -> 0.23300838 | H44: =H43/H23 -> 0.27874818 | I44: =I43/I23 -> 0.20311929
B45: Gold on loan, % of sales | G45: =G34/G23 -> 0.10455328 | H45: =H34/H23 -> 0.12918486 | I45: =I34/I23 -> 0.183481
B47: 3 CAPITAL STRUCTURE AND WACC (FY2026 balance sheet, market value of equity)
B48: Debt, FY2026 | C48: =IF($C$11="Debt",I33,I33-I34) -> 14551 | D48: Borrowings incl. lease liabilities; gold on loan only if treated as debt
B49: Debt, FY2025 | C49: =IF($C$11="Debt",H33,H33-H34) -> 12967
B50: Interest on that debt, FY2026 | C50: =IF($C$11="Debt",I25,I25-C12*AVERAGE(H34:I34)) -> 941.2 | D50: Reported interest less the assumed gold-loan fee when gold on loan is operating
B51: Pre-tax cost of debt | C51: =C50/AVERAGE(C48:C49) -> 0.068406134 | D51: Interest / average debt
B52: Market value of equity | C52: =C6*C8/10 -> 401897.3 | D52: Price × diluted shares
B53: Debt weight | C53: =C48/(C48+C52) -> 0.034940712
B54: WACC (computed) | C54: =(C52*C10+C48*C51*(1-C9))/(C52+C48) -> 0.10080364
B55: WACC used | C55: =IF(C18="",C54,C18) -> 0.10080364
B56: Gold-loan fee, % of sales | C56: =IF($C$11="Debt",0,C12*AVERAGE(G45:I45)) -> 0.002781461
B57: EBIT margin after the gold-loan fee | C57: =C13-C56 -> 0.091734819
B58: Net debt, FY2026 | C58: =C48-I32 -> 12634 | D58: Debt less cash & bank (investments not counted)
B60: 4 FREE CASH FLOW FORECAST (₹ crore; fiscal years end 31 March)
B61: Fiscal year | I61: 2026 | J61: 2027 | K61: 2028 | L61: 2029 | M61: 2030 | N61: 2031 | O61: 2032 | P61: 2033 | Q61: 2034 | R61: 2035 | S61: 2036 | T61: 2037 | U61: 2038 | V61: 2039 | W61: 2040 | X61: 2041 | Y61: 2042
B62: Revenue growth (Valuation sheet) | J62: =Valuation!N42 -> 0.1719361 | K62: =Valuation!O42 -> 0.1760922 | L62: =Valuation!P42 -> 0.17038176 | M62: =Valuation!Q42 -> 0.1686832 | N62: =Valuation!R42 -> 0.16395411 | O62: =Valuation!S42 -> 0.15674569 | P62: =Valuation!T42 -> 0.14760889 | Q62: =Valuation!U42 -> 0.1370947 | ... Y62: =Valuation!AC42 -> 0.06951
B63: Sales | I63: =I23 -> 87584 | J63: =I63*(1+J62) -> 102642.85 | K63: =J63*(1+K62) -> 120717.46 | L63: =K63*(1+L62) -> 141285.51 | M63: =L63*(1+M62) -> 165118 | N63: =M63*(1+N62) -> 192189.77 | O63: =N63*(1+O62) -> 222314.69 | P63: =O63*(1+P62) -> 255130.32 | Q63: =P63*(1+Q62) -> 290107.33 | ... Y63: =X63*(1+Y62) -> 585201.47
B64: EBIT, after the gold-loan fee | J64: =J63*$C$57 -> 9415.9234 | K64: =K63*$C$57 -> 11073.994 | L64: =L63*$C$57 -> 12960.801 | M64: =M63*$C$57 -> 15147.07 | N64: =N63*$C$57 -> 17630.494 | O64: =O63*$C$57 -> 20393.998 | P64: =P63*$C$57 -> 23404.334 | Q64: =Q63*$C$57 -> 26612.944 | ... Y64: =Y63*$C$57 -> 53683.351
B65: NOPAT = EBIT × (1 − tax) | J65: =J64*(1-$C$9) -> 7045.9355 | K65: =K64*(1-$C$9) -> 8286.6697 | L65: =L64*(1-$C$9) -> 9698.567 | M65: =M64*(1-$C$9) -> 11334.552 | N65: =N64*(1-$C$9) -> 13192.899 | O65: =O64*(1-$C$9) -> 15260.829 | P65: =P64*(1-$C$9) -> 17513.463 | Q65: =Q64*(1-$C$9) -> 19914.466 | ... Y65: =Y64*(1-$C$9) -> 40171.252
B66: Net capex = sales × (capex % − D&A %) | J66: =J63*($C$15-$C$14) -> 1375.342 | K66: =K63*($C$15-$C$14) -> 1617.529 | L66: =L63*($C$15-$C$14) -> 1893.1264 | M66: =M63*($C$15-$C$14) -> 2212.4651 | N66: =N63*($C$15-$C$14) -> 2575.2078 | O66: =O63*($C$15-$C$14) -> 2978.8605 | P66: =P63*($C$15-$C$14) -> 3418.5668 | Q66: =Q63*($C$15-$C$14) -> 3887.2342 | ... Y66: =Y63*($C$15-$C$14) -> 7841.2882
B67: Working capital | I67: =IF($C$11="Debt",I41,I43) -> 17790 | J67: =J63*$C$16 -> 24458.965 | K67: =K63*$C$16 -> 28765.998 | L67: =L63*$C$16 -> 33667.199 | M67: =M63*$C$16 -> 39346.29 | N67: =N63*$C$16 -> 45797.276 | O67: =O63*$C$16 -> 52975.801 | P67: =P63*$C$16 -> 60795.501 | Q67: =Q63*$C$16 -> 69130.242 | ... Y67: =Y63*$C$16 -> 139448.8
B68: Increase in working capital | J68: =J67-I67 -> 6668.9651 | K68: =K67-J67 -> 4307.0329 | L68: =L67-K67 -> 4901.2012 | M68: =M67-L67 -> 5679.0909 | N68: =N67-M67 -> 6450.9859 | O68: =O67-N67 -> 7178.5254 | P68: =P67-O67 -> 7819.6995 | Q68: =Q67-P67 -> 8334.7409 | ... Y68: =Y67-X67 -> 9063.1094
B69: Free cash flow to the firm (FCFF) | J69: =J65-J66-J68 -> -998.3717 | K69: =K65-K66-K68 -> 2362.1078 | L69: =L65-L66-L68 -> 2904.2394 | M69: =M65-M66-M68 -> 3442.9964 | N69: =N65-N66-N68 -> 4166.7051 | O69: =O65-O66-O68 -> 5103.4428 | P69: =P65-P66-P68 -> 6275.1965 | Q69: =Q65-Q66-Q68 -> 7692.4906 | ... Y69: =Y65-Y66-Y68 -> 23266.854
B70: Discount period (years from the price date) | J70: =$C$19 -> 0.49589041 | K70: =J70+1 -> 1.4958904 | L70: =K70+1 -> 2.4958904 | M70: =L70+1 -> 3.4958904 | N70: =M70+1 -> 4.4958904 | O70: =N70+1 -> 5.4958904 | P70: =O70+1 -> 6.4958904 | Q70: =P70+1 -> 7.4958904 | R70: =Q70+1 -> 8.4958904 | ... Y70: =X70+1 -> 15.49589
B71: Discount factor | J71: =1/(1+$C$55)^J70 -> 0.95349075 | K71: =1/(1+$C$55)^K70 -> 0.86617696 | L71: =1/(1+$C$55)^L70 -> 0.78685873 | M71: =1/(1+$C$55)^M70 -> 0.7148039 | N71: =1/(1+$C$55)^N70 -> 0.64934733 | O71: =1/(1+$C$55)^O70 -> 0.58988479 | P71: =1/(1+$C$55)^P70 -> 0.53586741 | Q71: =1/(1+$C$55)^Q70 -> 0.48679654 | ... Y71: =1/(1+$C$55)^Y70 -> 0.22577125
B72: Share of the year counted | J72: =$C$19 -> 0.49589041 | K72: =1 -> 1 | L72: =1 -> 1 | M72: =1 -> 1 | N72: =1 -> 1 | O72: =1 -> 1 | P72: =1 -> 1 | Q72: =1 -> 1 | R72: =1 -> 1 | ... Y72: =1 -> 1
B73: PV of FCFF | J73: =J69*J72*J71 -> -472.05701 | K73: =K69*K72*K71 -> 2046.0034 | L73: =L69*L72*L71 -> 2285.2261 | M73: =M69*M72*M71 -> 2461.0672 | N73: =N69*N72*N71 -> 2705.6388 | O73: =O69*O72*O71 -> 3010.4433 | P73: =P69*P72*P71 -> 3362.6733 | Q73: =Q69*Q72*Q71 -> 3744.6778 | ... Y73: =Y69*Y72*Y71 -> 5252.9867
B75: 5 VALUATION
B76: PV of FCFF, FY2027 stub to FY2042 | C76: =SUM(J73:Y73) -> 58989.857
B77: FY2043 sales | C77: =Y63*(1+C17) -> 620313.56
B78: FY2043 FCFF | C78: =C77*C57*(1-C9)-C77*(C15-C14)-(C77-Y63)*C16 -> 25902.833
B79: Terminal value at FY2042 = FCFF FY2043 / (WACC − g) | C79: =C78/(C55-C17) -> 634816.75
B80: PV of terminal value | C80: =C79*Y71 -> 143323.37
B81: Enterprise value | C81: =C76+C80 -> 202313.23
B82: Less: net debt | C82: =C58 -> 12634
B83: Equity value | C83: =C81-C82 -> 189679.23
B84: FCFF DCF value per share (₹) | C84: =C83/C8*10 -> 2131.2273
B85: vs price: upside / (downside) | C85: =C84/C6-1 -> -0.52804056
B86: Terminal value as % of enterprise value | C86: =C80/C81 -> 0.70842313
B87: Terminal value / FY2042 EBITDA | C87: =C79/(Y63*(C57+C14)) -> 10.517101
B88: Discounted-earnings value (Valuation sheet), for comparison | C88: =ValuePerShare -> 4057.5127
B90: 6 SENSITIVITY: FCFF DCF VALUE PER SHARE (₹), WACC (rows) × terminal growth (columns)
C91: =C84 -> 2131.2273 | D91: 0.05 | E91: 0.055 | F91: 0.06 | G91: 0.065 | H91: 0.07
C92: =$C$54+(-0.01) -> 0.090803639 | D92: 2515.3267 | E92: 2741.3778 | F92: 3040.8135 | G92: 3456.2932 | H92: 4071.4878
C93: =$C$54+(-0.005) -> 0.095803639 | D93: 2154.4474 | E93: 2315.1571 | F93: 2520.7531 | G93: 2793.0931 | H93: 3170.9765
C94: =$C$54+(0) -> 0.10080364 | D94: 1867.7342 | E94: 1985.0991 | F94: 2131.2273 | G94: 2318.1692 | H94: 2565.7995
C95: =$C$54+(0.005) -> 0.10580364 | D95: 1635.0826 | E95: 1722.6491 | F95: 1829.3333 | G95: 1962.1633 | H95: 2132.0929
C96: =$C$54+(0.01) -> 0.11080364 | D96: 1443.0115 | E96: 1509.4959 | F96: 1589.067 | G96: 1686.0102 | H96: 1806.7119
B98: 7 METHOD AND LIMITATIONS
B99: FCFF = EBIT × (1 − tax) − (capex − D&A) − increase in working capital. Discounted at the WACC to each 31-March year-end from the price date; only the part of FY2027 still ahead is counted, as on the Valuation sheet.
B100: Base case treats gold on loan as operating working-capital funding, as Titan reports it separately from borrowings and ICICI Direct carries it in current liabilities. Its cost (my 2% assumption) is charged against EBIT. Set C11 to Debt to treat it as debt instead.
B101: Margins, capex and D&A are five-year averages (FY2022-FY2026); working capital uses FY2024-FY2026, the years with a gold-on-loan split. Capex includes new right-of-use (store lease) assets, so lease liabilities stay in debt.
B102: Not adjusted: investments (only cash & bank is netted), minority interests (e.g. Damas), and the FY2027 cash already generated before the price date.
B103: Sources: Screener.in consolidated financials (retrieved 1-Oct-2026); ICICI Direct Q4FY26 result update (gold on loan); Titan Q4FY26 results (standalone gold on loan ₹14,314 cr). For education only; not investment advice.

Sheet Valuation
B2: Titan Company Ltd (NSE: TITAN): Discounted-Earnings Valuation
B3: Prepared by Daksh Chaudhary · updated 4-Oct-2026 · Base case, via Net Income · ₹ bn unless stated
B5: VALUATION ASSUMPTIONS
B6: Revenue Growth | C6: =(AC41/M41)^(1/AC40)-1 -> 0.12604317
B7: Net Margin | C7: =TEXT(MarginStart,"0.0%")&" → "&TEXT(MarginEnd,"0.0%") -> 6.7% → 6.6%
B8: Forecast Period | C8: =(AC40-1)&" years" -> 15 years
B10: MODEL SETTINGS
B11: Template | C11: via Net Income
B12: Discount Rate | C12: =DiscountRate -> 0.1026
B13: Exit Multiple | C13: =ExitMultiple -> 26.522648
B15: VALUATION RESULT
B16: VALUE PER SHARE
B17: =ValuePerShare -> 4057.5127 | C17: =C69 -> Overvaluation 10%
B18: ="vs. market price "&TEXT(Price,"#,##0.0")&" INR · value is "&TEXT(ABS(C68),"0.0%")&IF(C68<0," below"," above")&" the price" -> vs. market price 4,515.7 INR · value is 10.1% below the price
B20: Blue = input | Black = formula | Green = link to Data sheet
B24: 1 INPUTS & ASSUMPTIONS
B25: Current share price (₹) | C25: 4515.7 | D25: Last close as of 1-Oct-2026 (NSE: TITAN)
B26: Diluted shares outstanding (mn) | C26: 890 | D26: Diluted share count (basic ≈ 887.8 mn)
B27: Revenue growth mode | C27: Base case (per year) | D27: Base case = per-year path in row 43; Constant CAGR = C28 in every year
B28: Constant revenue growth (CAGR mode only) | C28: 0.126 | D28: Used only in Constant CAGR mode
B29: Net margin, start (fade anchor) | C29: 0.067105625 | D29: Fades along an S-curve to the FY2042 margin
B30: Net margin, end (FY2042) | C30: 0.06628 | D30: Long-term net margin
B31: Discount rate (cost of equity) | C31: 0.1026 | D31: Required return on equity
B32: Exit multiple (P/E on FY2042 net income) | C32: 26.522648 | D32: Terminal P/E applied to FY2042 net income
B33: Net adjustments / equity bridge (₹ bn) | C33: 0 | D33: Cash / debt adjustments (none applied)
B34: Price date (valuation date) | C34: =DATE(2026,10,1) -> 46296 | D34: NSE close used for the price in C25; the stub runs from here to 31-Mar-2027
B35: Share of FY2027 still ahead (stub) | C35: =(DATE(2027,3,31)-C34)/365 -> 0.49589041 | D35: Share of FY2027 net income still ahead of the price date; discount periods = stub, stub + 1, … years
B37: 2 FORECAST (₹ bn; fiscal years end 31 March)
B38: Fiscal year | C38: Unit | D38: 2017 | E38: 2018 | F38: 2019 | G38: 2020 | H38: 2021 | I38: 2022 | J38: 2023 | K38: 2024 | L38: 2025 | M38: 2026 | N38: 2027 | O38: 2028 | P38: 2029 | Q38: 2030 | R38: 2031 | S38: 2032 | T38: 2033 | U38: 2034 | V38: 2035 | W38: 2036 | X38: 2037 | Y38: 2038 | Z38: 2039 | AA38: 2040 | AB38: 2041 | AC38: 2042
B39: Period | D39: Actual | E39: Actual | F39: Actual | G39: Actual | H39: Actual | I39: Actual | J39: Actual | K39: Actual | L39: Actual | M39: Actual | N39: Forecast | O39: Forecast | P39: Forecast | Q39: Forecast | R39: Forecast | S39: Forecast | T39: Forecast | U39: Forecast | V39: Forecast | W39: Forecast | X39: Forecast | Y39: Forecast | Z39: Forecast | AA39: Forecast | AB39: Forecast | AC39: Forecast
B40: Forecast year (t) | N40: 1 | O40: =N40+1 -> 2 | P40: =O40+1 -> 3 | Q40: =P40+1 -> 4 | R40: =Q40+1 -> 5 | S40: =R40+1 -> 6 | T40: =S40+1 -> 7 | U40: =T40+1 -> 8 | V40: =U40+1 -> 9 | ... AC40: =AB40+1 -> 16
B41: Revenue | C41: ₹ bn | D41: =Data!C7/100 -> 133.821 | E41: =Data!C8/100 -> 161.56 | F41: =Data!C9/100 -> 197.785 | G41: =Data!C10/100 -> 210.515 | H41: =Data!C11/100 -> 216.44 | I41: =Data!C12/100 -> 287.99 | J41: =Data!C13/100 -> 405.75 | K41: =Data!C14/100 -> 510.84 | L41: =Data!C15/100 -> 604.56 | M41: =Data!C16/100 -> 875.84 | N41: =M41*(1+N42) -> 1026.4285 | O41: =N41*(1+O42) -> 1207.1746 | P41: =O41*(1+P42) -> 1412.8551 | Q41: =P41*(1+Q42) -> 1651.18 | R41: =Q41*(1+R42) -> 1921.8977 | S41: =R41*(1+S42) -> 2223.1469 | T41: =S41*(1+T42) -> 2551.3032 | U41: =T41*(1+U42) -> 2901.0733 | ... AC41: =AB41*(1+AC42) -> 5852.0147
B42: Revenue growth | C42: % | E42: =IF(D41=0,0,E41/D41-1) -> 0.20728436 | F42: =IF(E41=0,0,F41/E41-1) -> 0.2242201 | G42: =IF(F41=0,0,G41/F41-1) -> 0.064362818 | H42: =IF(G41=0,0,H41/G41-1) -> 0.028145263 | I42: =IF(H41=0,0,I41/H41-1) -> 0.3305766 | J42: =IF(I41=0,0,J41/I41-1) -> 0.40890309 | K42: =IF(J41=0,0,K41/J41-1) -> 0.25900185 | L42: =IF(K41=0,0,L41/K41-1) -> 0.18346253 | M42: =IF(L41=0,0,M41/L41-1) -> 0.44872304 | N42: =IF(GrowthMode="Constant CAGR",ConstGrowth,N43) -> 0.1719361 | O42: =IF(GrowthMode="Constant CAGR",ConstGrowth,O43) -> 0.1760922 | P42: =IF(GrowthMode="Constant CAGR",ConstGrowth,P43) -> 0.17038176 | Q42: =IF(GrowthMode="Constant CAGR",ConstGrowth,Q43) -> 0.1686832 | R42: =IF(GrowthMode="Constant CAGR",ConstGrowth,R43) -> 0.16395411 | S42: =IF(GrowthMode="Constant CAGR",ConstGrowth,S43) -> 0.15674569 | T42: =IF(GrowthMode="Constant CAGR",ConstGrowth,T43) -> 0.14760889 | U42: =IF(GrowthMode="Constant CAGR",ConstGrowth,U43) -> 0.1370947 | ... AC42: =IF(GrowthMode="Constant CAGR",ConstGrowth,AC43) -> 0.06951
B43: Revenue growth, base case (input) | C43: % input | N43: 0.1719361 | O43: 0.1760922 | P43: 0.17038176 | Q43: 0.1686832 | R43: 0.16395411 | S43: 0.15674569 | T43: 0.14760889 | U43: 0.1370947 | V43: 0.12575406 | W43: 0.11413794 | X43: 0.1027973 | Y43: 0.092283105 | Z43: 0.083146315 | AA43: 0.075937893 | AB43: 0.0712088 | AC43: 0.06951
B44: Net margin | C44: % | D44: =IF(D41=0,0,D46/D41) -> 0.053168038 | E44: =IF(E41=0,0,E46/E41) -> 0.069949245 | F44: =IF(F41=0,0,F46/F41) -> 0.070996284 | G44: =IF(G41=0,0,G46/G41) -> 0.071320333 | H44: =IF(H41=0,0,H46/H41) -> 0.044954722 | I44: =IF(I41=0,0,I46/I41) -> 0.075454009 | J44: =IF(J41=0,0,J46/J41) -> 0.080098583 | K44: =IF(K41=0,0,K46/K41) -> 0.068436301 | ... M44: =IF(M41=0,0,M46/M41) -> 0.057921538 | N44: =MarginStart+(MarginEnd-MarginStart)*N45 -> 0.067096353 | O44: =MarginStart+(MarginEnd-MarginStart)*O45 -> 0.067070149 | P44: =MarginStart+(MarginEnd-MarginStart)*P45 -> 0.067029432 | Q44: =MarginStart+(MarginEnd-MarginStart)*Q45 -> 0.066976621 | R44: =MarginStart+(MarginEnd-MarginStart)*R45 -> 0.066914135 | S44: =MarginStart+(MarginEnd-MarginStart)*S45 -> 0.066844392 | T44: =MarginStart+(MarginEnd-MarginStart)*T45 -> 0.066769812 | U44: =MarginStart+(MarginEnd-MarginStart)*U45 -> 0.066692813 | ... AC44: =MarginStart+(MarginEnd-MarginStart)*AC45 -> 0.06628
B45: Margin fade weight (S-curve, 0 → 1) | C45: weight | N45: =3*(N$40/$AC$40)^2-2*(N$40/$AC$40)^3 -> 0.011230469 | O45: =3*(O$40/$AC$40)^2-2*(O$40/$AC$40)^3 -> 0.04296875 | P45: =3*(P$40/$AC$40)^2-2*(P$40/$AC$40)^3 -> 0.092285156 | Q45: =3*(Q$40/$AC$40)^2-2*(Q$40/$AC$40)^3 -> 0.15625 | R45: =3*(R$40/$AC$40)^2-2*(R$40/$AC$40)^3 -> 0.23193359 | S45: =3*(S$40/$AC$40)^2-2*(S$40/$AC$40)^3 -> 0.31640625 | T45: =3*(T$40/$AC$40)^2-2*(T$40/$AC$40)^3 -> 0.40673828 | U45: =3*(U$40/$AC$40)^2-2*(U$40/$AC$40)^3 -> 0.5 | ... AC45: =3*(AC$40/$AC$40)^2-2*(AC$40/$AC$40)^3 -> 1
B46: Net income | C46: ₹ bn | D46: =Data!D7/100 -> 7.115 | E46: =Data!D8/100 -> 11.301 | F46: =Data!D9/100 -> 14.042 | G46: =Data!D10/100 -> 15.014 | H46: =Data!D11/100 -> 9.73 | I46: =Data!D12/100 -> 21.73 | J46: =Data!D13/100 -> 32.5 | K46: =Data!D14/100 -> 34.96 | L46: =Data!D15/100 -> 33.37 | M46: =Data!D16/100 -> 50.73 | N46: =N41*N44 -> 68.86961 | O46: =O41*O44 -> 80.965378 | P46: =P41*P44 -> 94.702874 | Q46: =Q41*Q44 -> 110.59046 | R46: =R41*R44 -> 128.60212 | S46: =S41*S44 -> 148.6049 | T46: =T41*T44 -> 170.35003 | U46: =U41*U44 -> 193.48074 | ... AC46: =AC41*AC44 -> 387.87154
B47: Net income growth | C47: % | E47: =IF(D46=0,0,E46/D46-1) -> 0.5883345 | F47: =IF(E46=0,0,F46/E46-1) -> 0.24254491 | G47: =IF(F46=0,0,G46/F46-1) -> 0.069220909 | H47: =IF(G46=0,0,H46/G46-1) -> -0.35193819 | I47: =IF(H46=0,0,I46/H46-1) -> 1.2332991 | J47: =IF(I46=0,0,J46/I46-1) -> 0.49562816 | K47: =IF(J46=0,0,K46/J46-1) -> 0.075692308 | L47: =IF(K46=0,0,L46/K46-1) -> -0.045480549 | ... AC47: =IF(AB46=0,0,AC46/AB46-1) -> 0.069360403
B49: 3 DISCOUNTING (cash flow to equity = net income)
B50: Share of fiscal year counted | C50: share | N50: =IF(N$40=1,StubFraction,1) -> 0.49589041 | O50: =IF(O$40=1,StubFraction,1) -> 1 | P50: =IF(P$40=1,StubFraction,1) -> 1 | Q50: =IF(Q$40=1,StubFraction,1) -> 1 | R50: =IF(R$40=1,StubFraction,1) -> 1 | S50: =IF(S$40=1,StubFraction,1) -> 1 | T50: =IF(T$40=1,StubFraction,1) -> 1 | U50: =IF(U$40=1,StubFraction,1) -> 1 | ... AC50: =IF(AC$40=1,StubFraction,1) -> 1
B51: Cash flow to equity (net income × share) | C51: ₹ bn | N51: =N46*N50 -> 34.151779 | O51: =O46*O50 -> 80.965378 | P51: =P46*P50 -> 94.702874 | Q51: =Q46*Q50 -> 110.59046 | R51: =R46*R50 -> 128.60212 | S51: =S46*S50 -> 148.6049 | T51: =T46*T50 -> 170.35003 | U51: =U46*U50 -> 193.48074 | ... AC51: =AC46*AC50 -> 387.87154
B52: Discount period (years from valuation date) | C52: years | N52: =StubFraction+N$40-1 -> 0.49589041 | O52: =StubFraction+O$40-1 -> 1.4958904 | P52: =StubFraction+P$40-1 -> 2.4958904 | Q52: =StubFraction+Q$40-1 -> 3.4958904 | R52: =StubFraction+R$40-1 -> 4.4958904 | S52: =StubFraction+S$40-1 -> 5.4958904 | T52: =StubFraction+T$40-1 -> 6.4958904 | U52: =StubFraction+U$40-1 -> 7.4958904 | ... AC52: =StubFraction+AC$40-1 -> 15.49589
B53: Discount factor = 1 / (1 + r)^period | C53: factor | N53: =1/(1+DiscountRate)^N52 -> 0.9527201 | O53: =1/(1+DiscountRate)^O52 -> 0.86406684 | P53: =1/(1+DiscountRate)^P52 -> 0.78366301 | Q53: =1/(1+DiscountRate)^Q52 -> 0.71074099 | R53: =1/(1+DiscountRate)^R52 -> 0.64460456 | S53: =1/(1+DiscountRate)^S52 -> 0.58462231 | T53: =1/(1+DiscountRate)^T52 -> 0.53022158 | U53: =1/(1+DiscountRate)^U52 -> 0.48088298 | ... AC53: =1/(1+DiscountRate)^AC52 -> 0.22013825
B54: Present value | C54: ₹ bn | N54: =N51*N53 -> 32.537086 | O54: =O51*O53 -> 69.959498 | P54: =P51*P53 -> 74.215139 | Q54: =Q51*Q53 -> 78.601171 | R54: =R51*R53 -> 82.897516 | S54: =S51*S53 -> 86.877743 | T54: =T51*T53 -> 90.323263 | U54: =U51*U53 -> 93.041595 | ... AC54: =AC51*AC53 -> 85.38536
B56: 4 VALUATION
B57: PV of forecast cash flows (₹ bn) | C57: =SUM(N54:AC54) -> 1346.5405
B58: FY2042 net income (₹ bn) | C58: =AC46 -> 387.87154
B59: Exit multiple (P/E) | C59: =ExitMultiple -> 26.522648
B60: Terminal value at FY2042 (₹ bn) | C60: =C58*C59 -> 10287.38
B61: Discount factor for FY2042 | C61: =AC53 -> 0.22013825
B62: PV of terminal value (₹ bn) | C62: =C60*C61 -> 2264.6458
B63: Net adjustments / equity bridge (₹ bn) | C63: =NetAdj -> 0
B64: Equity value (₹ bn) | C64: =C57+C62+C63 -> 3611.1863
B65: Diluted shares (mn) | C65: =Shares -> 890
B66: Value per share (₹) | C66: =IF(C65=0,0,C64/C65*1000) -> 4057.5127
B67: Current share price (₹) | C67: =Price -> 4515.7
B68: Value vs price: upside / (downside) | C68: =IF(C67=0,0,C66/C67-1) -> -0.1014654
B69: Verdict | C69: =IF(C66<C67,"Overvaluation","Undervaluation")&" "&TEXT(ABS(C68),"0%") -> Overvaluation 10%
B70: Terminal value as % of equity value | C70: =IF(C64=0,0,C62/C64) -> 0.62711963
B74: 5 SENSITIVITY: VALUE PER SHARE (₹)
B75: Discount rate (rows) × exit P/E (columns) | J75: Rate step | K75: 0.005
C76: r \ P/E → | D76: =ExitMultiple+(-2)*$K$76 -> 20.522648 | E76: =ExitMultiple+(-1)*$K$76 -> 23.522648 | F76: =ExitMultiple+(0)*$K$76 -> 26.522648 | G76: =ExitMultiple+(1)*$K$76 -> 29.522648 | H76: =ExitMultiple+(2)*$K$76 -> 32.522648 | J76: P/E step | K76: 3
C77: =DiscountRate+(-2)*$K$75 -> 0.0926 | D77: =IF(Shares=0,0,(SUMPRODUCT($N$51:$AC$51/(1+$C77)^$N$52:$AC$52)+$C$58*D$76/(1+$C77)^$AC$52+NetAdj)/Shares*1000) -> 3904.2151 | E77: =IF(Shares=0,0,(SUMPRODUCT($N$51:$AC$51/(1+$C77)^$N$52:$AC$52)+$C$58*E$76/(1+$C77)^$AC$52+NetAdj)/Shares*1000) -> 4235.6732 | F77: =IF(Shares=0,0,(SUMPRODUCT($N$51:$AC$51/(1+$C77)^$N$52:$AC$52)+$C$58*F$76/(1+$C77)^$AC$52+NetAdj)/Shares*1000) -> 4567.1314 | G77: =IF(Shares=0,0,(SUMPRODUCT($N$51:$AC$51/(1+$C77)^$N$52:$AC$52)+$C$58*G$76/(1+$C77)^$AC$52+NetAdj)/Shares*1000) -> 4898.5895 | H77: =IF(Shares=0,0,(SUMPRODUCT($N$51:$AC$51/(1+$C77)^$N$52:$AC$52)+$C$58*H$76/(1+$C77)^$AC$52+NetAdj)/Shares*1000) -> 5230.0476
C78: =DiscountRate+(-1)*$K$75 -> 0.0976 | D78: =IF(Shares=0,0,(SUMPRODUCT($N$51:$AC$51/(1+$C78)^$N$52:$AC$52)+$C$58*D$76/(1+$C78)^$AC$52+NetAdj)/Shares*1000) -> 3685.7801 | E78: =IF(Shares=0,0,(SUMPRODUCT($N$51:$AC$51/(1+$C78)^$N$52:$AC$52)+$C$58*E$76/(1+$C78)^$AC$52+NetAdj)/Shares*1000) -> 3994.5976 | F78: =IF(Shares=0,0,(SUMPRODUCT($N$51:$AC$51/(1+$C78)^$N$52:$AC$52)+$C$58*F$76/(1+$C78)^$AC$52+NetAdj)/Shares*1000) -> 4303.415 | G78: =IF(Shares=0,0,(SUMPRODUCT($N$51:$AC$51/(1+$C78)^$N$52:$AC$52)+$C$58*G$76/(1+$C78)^$AC$52+NetAdj)/Shares*1000) -> 4612.2325 | H78: =IF(Shares=0,0,(SUMPRODUCT($N$51:$AC$51/(1+$C78)^$N$52:$AC$52)+$C$58*H$76/(1+$C78)^$AC$52+NetAdj)/Shares*1000) -> 4921.0499
C79: =DiscountRate+(0)*$K$75 -> 0.1026 | D79: =IF(Shares=0,0,(SUMPRODUCT($N$51:$AC$51/(1+$C79)^$N$52:$AC$52)+$C$58*D$76/(1+$C79)^$AC$52+NetAdj)/Shares*1000) -> 3481.8811 | E79: =IF(Shares=0,0,(SUMPRODUCT($N$51:$AC$51/(1+$C79)^$N$52:$AC$52)+$C$58*E$76/(1+$C79)^$AC$52+NetAdj)/Shares*1000) -> 3769.6969 | F79: =IF(Shares=0,0,(SUMPRODUCT($N$51:$AC$51/(1+$C79)^$N$52:$AC$52)+$C$58*F$76/(1+$C79)^$AC$52+NetAdj)/Shares*1000) -> 4057.5127 | G79: =IF(Shares=0,0,(SUMPRODUCT($N$51:$AC$51/(1+$C79)^$N$52:$AC$52)+$C$58*G$76/(1+$C79)^$AC$52+NetAdj)/Shares*1000) -> 4345.3285 | H79: =IF(Shares=0,0,(SUMPRODUCT($N$51:$AC$51/(1+$C79)^$N$52:$AC$52)+$C$58*H$76/(1+$C79)^$AC$52+NetAdj)/Shares*1000) -> 4633.1444 | I79: → base case
C80: =DiscountRate+(1)*$K$75 -> 0.1076 | D80: =IF(Shares=0,0,(SUMPRODUCT($N$51:$AC$51/(1+$C80)^$N$52:$AC$52)+$C$58*D$76/(1+$C80)^$AC$52+NetAdj)/Shares*1000) -> 3291.4579 | E80: =IF(Shares=0,0,(SUMPRODUCT($N$51:$AC$51/(1+$C80)^$N$52:$AC$52)+$C$58*E$76/(1+$C80)^$AC$52+NetAdj)/Shares*1000) -> 3559.7858 | F80: =IF(Shares=0,0,(SUMPRODUCT($N$51:$AC$51/(1+$C80)^$N$52:$AC$52)+$C$58*F$76/(1+$C80)^$AC$52+NetAdj)/Shares*1000) -> 3828.1137 | G80: =IF(Shares=0,0,(SUMPRODUCT($N$51:$AC$51/(1+$C80)^$N$52:$AC$52)+$C$58*G$76/(1+$C80)^$AC$52+NetAdj)/Shares*1000) -> 4096.4417 | H80: =IF(Shares=0,0,(SUMPRODUCT($N$51:$AC$51/(1+$C80)^$N$52:$AC$52)+$C$58*H$76/(1+$C80)^$AC$52+NetAdj)/Shares*1000) -> 4364.7696
C81: =DiscountRate+(2)*$K$75 -> 0.1126 | D81: =IF(Shares=0,0,(SUMPRODUCT($N$51:$AC$51/(1+$C81)^$N$52:$AC$52)+$C$58*D$76/(1+$C81)^$AC$52+NetAdj)/Shares*1000) -> 3113.5332 | E81: =IF(Shares=0,0,(SUMPRODUCT($N$51:$AC$51/(1+$C81)^$N$52:$AC$52)+$C$58*E$76/(1+$C81)^$AC$52+NetAdj)/Shares*1000) -> 3363.7718 | F81: =IF(Shares=0,0,(SUMPRODUCT($N$51:$AC$51/(1+$C81)^$N$52:$AC$52)+$C$58*F$76/(1+$C81)^$AC$52+NetAdj)/Shares*1000) -> 3614.0103 | G81: =IF(Shares=0,0,(SUMPRODUCT($N$51:$AC$51/(1+$C81)^$N$52:$AC$52)+$C$58*G$76/(1+$C81)^$AC$52+NetAdj)/Shares*1000) -> 3864.2489 | H81: =IF(Shares=0,0,(SUMPRODUCT($N$51:$AC$51/(1+$C81)^$N$52:$AC$52)+$C$58*H$76/(1+$C81)^$AC$52+NetAdj)/Shares*1000) -> 4114.4875
B83: Revenue growth shift vs current path, every year (rows) × FY2042 net margin (columns) | J83: Growth step | K83: 0.02
C84: Δ growth \ margin → | D84: =MarginEnd+(-2)*$K$84 -> 0.05628 | E84: =MarginEnd+(-1)*$K$84 -> 0.06128 | F84: =MarginEnd+(0)*$K$84 -> 0.06628 | G84: =MarginEnd+(1)*$K$84 -> 0.07128 | H84: =MarginEnd+(2)*$K$84 -> 0.07628 | J84: Margin step | K84: 0.005
C85: =(-2)*$K$83 -> -0.04 | D85: =IF(Shares=0,0,(MarginStart*SUMPRODUCT($N$50:$AC$50,$N92:$AC92,$N$53:$AC$53)+(D$84-MarginStart)*SUMPRODUCT($N$50:$AC$50,$N92:$AC92,$N$45:$AC$45,$N$53:$AC$53)+$AC92*(MarginStart+(D$84-MarginStart)*$AC$45)*ExitMultiple*$AC$53+NetAdj)/Shares*1000) -> 2234.4239 | E85: =IF(Shares=0,0,(MarginStart*SUMPRODUCT($N$50:$AC$50,$N92:$AC92,$N$53:$AC$53)+(E$84-MarginStart)*SUMPRODUCT($N$50:$AC$50,$N92:$AC92,$N$45:$AC$45,$N$53:$AC$53)+$AC92*(MarginStart+(E$84-MarginStart)*$AC$45)*ExitMultiple*$AC$53+NetAdj)/Shares*1000) -> 2385.5298 | F85: =IF(Shares=0,0,(MarginStart*SUMPRODUCT($N$50:$AC$50,$N92:$AC92,$N$53:$AC$53)+(F$84-MarginStart)*SUMPRODUCT($N$50:$AC$50,$N92:$AC92,$N$45:$AC$45,$N$53:$AC$53)+$AC92*(MarginStart+(F$84-MarginStart)*$AC$45)*ExitMultiple*$AC$53+NetAdj)/Shares*1000) -> 2536.6357 | G85: =IF(Shares=0,0,(MarginStart*SUMPRODUCT($N$50:$AC$50,$N92:$AC92,$N$53:$AC$53)+(G$84-MarginStart)*SUMPRODUCT($N$50:$AC$50,$N92:$AC92,$N$45:$AC$45,$N$53:$AC$53)+$AC92*(MarginStart+(G$84-MarginStart)*$AC$45)*ExitMultiple*$AC$53+NetAdj)/Shares*1000) -> 2687.7416 | H85: =IF(Shares=0,0,(MarginStart*SUMPRODUCT($N$50:$AC$50,$N92:$AC92,$N$53:$AC$53)+(H$84-MarginStart)*SUMPRODUCT($N$50:$AC$50,$N92:$AC92,$N$45:$AC$45,$N$53:$AC$53)+$AC92*(MarginStart+(H$84-MarginStart)*$AC$45)*ExitMultiple*$AC$53+NetAdj)/Shares*1000) -> 2838.8474
C86: =(-1)*$K$83 -> -0.02 | D86: =IF(Shares=0,0,(MarginStart*SUMPRODUCT($N$50:$AC$50,$N93:$AC93,$N$53:$AC$53)+(D$84-MarginStart)*SUMPRODUCT($N$50:$AC$50,$N93:$AC93,$N$45:$AC$45,$N$53:$AC$53)+$AC93*(MarginStart+(D$84-MarginStart)*$AC$45)*ExitMultiple*$AC$53+NetAdj)/Shares*1000) -> 2809.2706 | E86: =IF(Shares=0,0,(MarginStart*SUMPRODUCT($N$50:$AC$50,$N93:$AC93,$N$53:$AC$53)+(E$84-MarginStart)*SUMPRODUCT($N$50:$AC$50,$N93:$AC93,$N$45:$AC$45,$N$53:$AC$53)+$AC93*(MarginStart+(E$84-MarginStart)*$AC$45)*ExitMultiple*$AC$53+NetAdj)/Shares*1000) -> 3006.6053 | F86: =IF(Shares=0,0,(MarginStart*SUMPRODUCT($N$50:$AC$50,$N93:$AC93,$N$53:$AC$53)+(F$84-MarginStart)*SUMPRODUCT($N$50:$AC$50,$N93:$AC93,$N$45:$AC$45,$N$53:$AC$53)+$AC93*(MarginStart+(F$84-MarginStart)*$AC$45)*ExitMultiple*$AC$53+NetAdj)/Shares*1000) -> 3203.94 | G86: =IF(Shares=0,0,(MarginStart*SUMPRODUCT($N$50:$AC$50,$N93:$AC93,$N$53:$AC$53)+(G$84-MarginStart)*SUMPRODUCT($N$50:$AC$50,$N93:$AC93,$N$45:$AC$45,$N$53:$AC$53)+$AC93*(MarginStart+(G$84-MarginStart)*$AC$45)*ExitMultiple*$AC$53+NetAdj)/Shares*1000) -> 3401.2747 | H86: =IF(Shares=0,0,(MarginStart*SUMPRODUCT($N$50:$AC$50,$N93:$AC93,$N$53:$AC$53)+(H$84-MarginStart)*SUMPRODUCT($N$50:$AC$50,$N93:$AC93,$N$45:$AC$45,$N$53:$AC$53)+$AC93*(MarginStart+(H$84-MarginStart)*$AC$45)*ExitMultiple*$AC$53+NetAdj)/Shares*1000) -> 3598.6094
C87: =(0)*$K$83 -> 0 | D87: =IF(Shares=0,0,(MarginStart*SUMPRODUCT($N$50:$AC$50,$N94:$AC94,$N$53:$AC$53)+(D$84-MarginStart)*SUMPRODUCT($N$50:$AC$50,$N94:$AC94,$N$45:$AC$45,$N$53:$AC$53)+$AC94*(MarginStart+(D$84-MarginStart)*$AC$45)*ExitMultiple*$AC$53+NetAdj)/Shares*1000) -> 3543.2524 | E87: =IF(Shares=0,0,(MarginStart*SUMPRODUCT($N$50:$AC$50,$N94:$AC94,$N$53:$AC$53)+(E$84-MarginStart)*SUMPRODUCT($N$50:$AC$50,$N94:$AC94,$N$45:$AC$45,$N$53:$AC$53)+$AC94*(MarginStart+(E$84-MarginStart)*$AC$45)*ExitMultiple*$AC$53+NetAdj)/Shares*1000) -> 3800.3826 | F87: =IF(Shares=0,0,(MarginStart*SUMPRODUCT($N$50:$AC$50,$N94:$AC94,$N$53:$AC$53)+(F$84-MarginStart)*SUMPRODUCT($N$50:$AC$50,$N94:$AC94,$N$45:$AC$45,$N$53:$AC$53)+$AC94*(MarginStart+(F$84-MarginStart)*$AC$45)*ExitMultiple*$AC$53+NetAdj)/Shares*1000) -> 4057.5127 | G87: =IF(Shares=0,0,(MarginStart*SUMPRODUCT($N$50:$AC$50,$N94:$AC94,$N$53:$AC$53)+(G$84-MarginStart)*SUMPRODUCT($N$50:$AC$50,$N94:$AC94,$N$45:$AC$45,$N$53:$AC$53)+$AC94*(MarginStart+(G$84-MarginStart)*$AC$45)*ExitMultiple*$AC$53+NetAdj)/Shares*1000) -> 4314.6429 | H87: =IF(Shares=0,0,(MarginStart*SUMPRODUCT($N$50:$AC$50,$N94:$AC94,$N$53:$AC$53)+(H$84-MarginStart)*SUMPRODUCT($N$50:$AC$50,$N94:$AC94,$N$45:$AC$45,$N$53:$AC$53)+$AC94*(MarginStart+(H$84-MarginStart)*$AC$45)*ExitMultiple*$AC$53+NetAdj)/Shares*1000) -> 4571.773 | I87: → base case
C88: =(1)*$K$83 -> 0.02 | D88: =IF(Shares=0,0,(MarginStart*SUMPRODUCT($N$50:$AC$50,$N95:$AC95,$N$53:$AC$53)+(D$84-MarginStart)*SUMPRODUCT($N$50:$AC$50,$N95:$AC95,$N$45:$AC$45,$N$53:$AC$53)+$AC95*(MarginStart+(D$84-MarginStart)*$AC$45)*ExitMultiple*$AC$53+NetAdj)/Shares*1000) -> 4479.1318 | E88: =IF(Shares=0,0,(MarginStart*SUMPRODUCT($N$50:$AC$50,$N95:$AC95,$N$53:$AC$53)+(E$84-MarginStart)*SUMPRODUCT($N$50:$AC$50,$N95:$AC95,$N$45:$AC$45,$N$53:$AC$53)+$AC95*(MarginStart+(E$84-MarginStart)*$AC$45)*ExitMultiple*$AC$53+NetAdj)/Shares*1000) -> 4813.3493 | F88: =IF(Shares=0,0,(MarginStart*SUMPRODUCT($N$50:$AC$50,$N95:$AC95,$N$53:$AC$53)+(F$84-MarginStart)*SUMPRODUCT($N$50:$AC$50,$N95:$AC95,$N$45:$AC$45,$N$53:$AC$53)+$AC95*(MarginStart+(F$84-MarginStart)*$AC$45)*ExitMultiple*$AC$53+NetAdj)/Shares*1000) -> 5147.5669 | G88: =IF(Shares=0,0,(MarginStart*SUMPRODUCT($N$50:$AC$50,$N95:$AC95,$N$53:$AC$53)+(G$84-MarginStart)*SUMPRODUCT($N$50:$AC$50,$N95:$AC95,$N$45:$AC$45,$N$53:$AC$53)+$AC95*(MarginStart+(G$84-MarginStart)*$AC$45)*ExitMultiple*$AC$53+NetAdj)/Shares*1000) -> 5481.7844 | H88: =IF(Shares=0,0,(MarginStart*SUMPRODUCT($N$50:$AC$50,$N95:$AC95,$N$53:$AC$53)+(H$84-MarginStart)*SUMPRODUCT($N$50:$AC$50,$N95:$AC95,$N$45:$AC$45,$N$53:$AC$53)+$AC95*(MarginStart+(H$84-MarginStart)*$AC$45)*ExitMultiple*$AC$53+NetAdj)/Shares*1000) -> 5816.002
C89: =(2)*$K$83 -> 0.04 | D89: =IF(Shares=0,0,(MarginStart*SUMPRODUCT($N$50:$AC$50,$N96:$AC96,$N$53:$AC$53)+(D$84-MarginStart)*SUMPRODUCT($N$50:$AC$50,$N96:$AC96,$N$45:$AC$45,$N$53:$AC$53)+$AC96*(MarginStart+(D$84-MarginStart)*$AC$45)*ExitMultiple*$AC$53+NetAdj)/Shares*1000) -> 5670.3965 | E89: =IF(Shares=0,0,(MarginStart*SUMPRODUCT($N$50:$AC$50,$N96:$AC96,$N$53:$AC$53)+(E$84-MarginStart)*SUMPRODUCT($N$50:$AC$50,$N96:$AC96,$N$45:$AC$45,$N$53:$AC$53)+$AC96*(MarginStart+(E$84-MarginStart)*$AC$45)*ExitMultiple*$AC$53+NetAdj)/Shares*1000) -> 6103.6619 | F89: =IF(Shares=0,0,(MarginStart*SUMPRODUCT($N$50:$AC$50,$N96:$AC96,$N$53:$AC$53)+(F$84-MarginStart)*SUMPRODUCT($N$50:$AC$50,$N96:$AC96,$N$45:$AC$45,$N$53:$AC$53)+$AC96*(MarginStart+(F$84-MarginStart)*$AC$45)*ExitMultiple*$AC$53+NetAdj)/Shares*1000) -> 6536.9272 | G89: =IF(Shares=0,0,(MarginStart*SUMPRODUCT($N$50:$AC$50,$N96:$AC96,$N$53:$AC$53)+(G$84-MarginStart)*SUMPRODUCT($N$50:$AC$50,$N96:$AC96,$N$45:$AC$45,$N$53:$AC$53)+$AC96*(MarginStart+(G$84-MarginStart)*$AC$45)*ExitMultiple*$AC$53+NetAdj)/Shares*1000) -> 6970.1926 | H89: =IF(Shares=0,0,(MarginStart*SUMPRODUCT($N$50:$AC$50,$N96:$AC96,$N$53:$AC$53)+(H$84-MarginStart)*SUMPRODUCT($N$50:$AC$50,$N96:$AC96,$N$45:$AC$45,$N$53:$AC$53)+$AC96*(MarginStart+(H$84-MarginStart)*$AC$45)*ExitMultiple*$AC$53+NetAdj)/Shares*1000) -> 7403.458
B91: Workings for the sensitivity table and chart
B92: ="Revenue path, growth shift "&TEXT(C85,"+0.0%;-0.0%;0.0%")&" (₹ bn)" -> Revenue path, growth shift -4.0% (₹ bn) | C92: =C85 -> -0.04 | N92: =$M$41*(1+N$42+$C92) -> 991.39491 | O92: =N92*(1+O$42+$C92) -> 1126.316 | P92: =O92*(1+P$42+$C92) -> 1273.1671 | Q92: =P92*(1+Q$42+$C92) -> 1437.0023 | R92: =Q92*(1+R$42+$C92) -> 1615.1246 | S92: =R92*(1+S$42+$C92) -> 1803.6835 | T92: =S92*(1+T$42+$C92) -> 1997.7758 | U92: =T92*(1+U$42+$C92) -> 2191.7493 | V92: =U92*(1+V$42+$C92) -> 2379.7007 | ... AC92: =AB92*(1+AC$42+$C92) -> 3279.6052
B93: ="Revenue path, growth shift "&TEXT(C86,"+0.0%;-0.0%;0.0%")&" (₹ bn)" -> Revenue path, growth shift -2.0% (₹ bn) | C93: =C86 -> -0.02 | N93: =$M$41*(1+N$42+$C93) -> 1008.9117 | O93: =N93*(1+O$42+$C93) -> 1166.395 | P93: =O93*(1+P$42+$C93) -> 1341.7995 | Q93: =P93*(1+Q$42+$C93) -> 1541.3025 | R93: =Q93*(1+R$42+$C93) -> 1763.1793 | S93: =R93*(1+S$42+$C93) -> 2004.2865 | T93: =S93*(1+T$42+$C93) -> 2260.0513 | U93: =T93*(1+U$42+$C93) -> 2524.6913 | V93: =U93*(1+V$42+$C93) -> 2791.6877 | ... AC93: =AB93*(1+AC$42+$C93) -> 4392.4064
B94: ="Revenue path, growth shift "&TEXT(C87,"+0.0%;-0.0%;0.0%")&" (₹ bn)" -> Revenue path, growth shift 0.0% (₹ bn) | C94: =C87 -> 0 | N94: =$M$41*(1+N$42+$C94) -> 1026.4285 | O94: =N94*(1+O$42+$C94) -> 1207.1746 | P94: =O94*(1+P$42+$C94) -> 1412.8551 | Q94: =P94*(1+Q$42+$C94) -> 1651.18 | R94: =Q94*(1+R$42+$C94) -> 1921.8977 | S94: =R94*(1+S$42+$C94) -> 2223.1469 | T94: =S94*(1+T$42+$C94) -> 2551.3032 | U94: =T94*(1+U$42+$C94) -> 2901.0733 | V94: =U94*(1+V$42+$C94) -> 3265.8951 | ... AC94: =AB94*(1+AC$42+$C94) -> 5852.0147
B95: ="Revenue path, growth shift "&TEXT(C88,"+0.0%;-0.0%;0.0%")&" (₹ bn)" -> Revenue path, growth shift +2.0% (₹ bn) | C95: =C88 -> 0.02 | N95: =$M$41*(1+N$42+$C95) -> 1043.9453 | O95: =N95*(1+O$42+$C95) -> 1248.6548 | P95: =O95*(1+P$42+$C95) -> 1486.3759 | Q95: =P95*(1+Q$42+$C95) -> 1766.8301 | R95: =Q95*(1+R$42+$C95) -> 2091.8458 | S95: =R95*(1+S$42+$C95) -> 2461.5705 | T95: =S95*(1+T$42+$C95) -> 2874.1516 | U95: =T95*(1+U$42+$C95) -> 3325.6656 | V95: =U95*(1+V$42+$C95) -> 3810.3948 | ... AC95: =AB95*(1+AC$42+$C95) -> 7757.302
B96: ="Revenue path, growth shift "&TEXT(C89,"+0.0%;-0.0%;0.0%")&" (₹ bn)" -> Revenue path, growth shift +4.0% (₹ bn) | C96: =C89 -> 0.04 | N96: =$M$41*(1+N$42+$C96) -> 1061.4621 | O96: =N96*(1+O$42+$C96) -> 1290.8358 | P96: =O96*(1+P$42+$C96) -> 1562.4041 | Q96: =P96*(1+Q$42+$C96) -> 1888.4516 | R96: =Q96*(1+R$42+$C96) -> 2273.609 | S96: =R96*(1+S$42+$C96) -> 2720.9318 | T96: =S96*(1+T$42+$C96) -> 3231.4028 | U96: =T96*(1+U$42+$C96) -> 3803.6671 | V96: =U96*(1+V$42+$C96) -> 4434.1404 | ... AC96: =AB96*(1+AC$42+$C96) -> 10232.804
B98: Chart: forecast shading (1 = forecast year) | D98: =IF(D$39="Forecast",1,0) -> 0 | E98: =IF(E$39="Forecast",1,0) -> 0 | F98: =IF(F$39="Forecast",1,0) -> 0 | G98: =IF(G$39="Forecast",1,0) -> 0 | H98: =IF(H$39="Forecast",1,0) -> 0 | I98: =IF(I$39="Forecast",1,0) -> 0 | J98: =IF(J$39="Forecast",1,0) -> 0 | K98: =IF(K$39="Forecast",1,0) -> 0 | ... AC98: =IF(AC$39="Forecast",1,0) -> 1
B99: Chart: revenue CAGR guide line (₹ bn) | D99: =IF(D$38=$M$38,$M$41,IF(D$38=$AC$38,$AC$41,IF(D$38=$U$38,($M$41+$AC$41)/2,NA()))) -> #N/A | E99: =IF(E$38=$M$38,$M$41,IF(E$38=$AC$38,$AC$41,IF(E$38=$U$38,($M$41+$AC$41)/2,NA()))) -> #N/A | F99: =IF(F$38=$M$38,$M$41,IF(F$38=$AC$38,$AC$41,IF(F$38=$U$38,($M$41+$AC$41)/2,NA()))) -> #N/A | G99: =IF(G$38=$M$38,$M$41,IF(G$38=$AC$38,$AC$41,IF(G$38=$U$38,($M$41+$AC$41)/2,NA()))) -> #N/A | H99: =IF(H$38=$M$38,$M$41,IF(H$38=$AC$38,$AC$41,IF(H$38=$U$38,($M$41+$AC$41)/2,NA()))) -> #N/A | I99: =IF(I$38=$M$38,$M$41,IF(I$38=$AC$38,$AC$41,IF(I$38=$U$38,($M$41+$AC$41)/2,NA()))) -> #N/A | J99: =IF(J$38=$M$38,$M$41,IF(J$38=$AC$38,$AC$41,IF(J$38=$U$38,($M$41+$AC$41)/2,NA()))) -> #N/A | K99: =IF(K$38=$M$38,$M$41,IF(K$38=$AC$38,$AC$41,IF(K$38=$U$38,($M$41+$AC$41)/2,NA()))) -> #N/A | ... AC99: =IF(AC$38=$M$38,$M$41,IF(AC$38=$AC$38,$AC$41,IF(AC$38=$U$38,($M$41+$AC$41)/2,NA()))) -> 5852.0147
B100: Chart: net income CAGR guide line (₹ bn) | D100: =IF(D$38=$M$38,$M$46,IF(D$38=$AC$38,$AC$46,IF(D$38=$U$38,($M$46+$AC$46)/2,NA()))) -> #N/A | E100: =IF(E$38=$M$38,$M$46,IF(E$38=$AC$38,$AC$46,IF(E$38=$U$38,($M$46+$AC$46)/2,NA()))) -> #N/A | F100: =IF(F$38=$M$38,$M$46,IF(F$38=$AC$38,$AC$46,IF(F$38=$U$38,($M$46+$AC$46)/2,NA()))) -> #N/A | G100: =IF(G$38=$M$38,$M$46,IF(G$38=$AC$38,$AC$46,IF(G$38=$U$38,($M$46+$AC$46)/2,NA()))) -> #N/A | H100: =IF(H$38=$M$38,$M$46,IF(H$38=$AC$38,$AC$46,IF(H$38=$U$38,($M$46+$AC$46)/2,NA()))) -> #N/A | I100: =IF(I$38=$M$38,$M$46,IF(I$38=$AC$38,$AC$46,IF(I$38=$U$38,($M$46+$AC$46)/2,NA()))) -> #N/A | J100: =IF(J$38=$M$38,$M$46,IF(J$38=$AC$38,$AC$46,IF(J$38=$U$38,($M$46+$AC$46)/2,NA()))) -> #N/A | K100: =IF(K$38=$M$38,$M$46,IF(K$38=$AC$38,$AC$46,IF(K$38=$U$38,($M$46+$AC$46)/2,NA()))) -> #N/A | ... AC100: =IF(AC$38=$M$38,$M$46,IF(AC$38=$AC$38,$AC$46,IF(AC$38=$U$38,($M$46+$AC$46)/2,NA()))) -> 387.87154
B101: Chart label: revenue CAGR | C101: =TEXT(C6,"0.0%")&" CAGR" -> 12.6% CAGR
B102: Chart label: net income CAGR | C102: =TEXT((AC46/M46)^(1/AC40)-1,"0.0%")&" CAGR" -> 13.6% CAGR
B103: Chart title | C103: =AC38&" · FORECAST" -> 2042 · FORECAST
B104: Chart legend: revenue | C104: ="Revenue "&TEXT(AC41/1000,"0.0")&"T" -> Revenue 5.9T
B105: Chart legend: net income | C105: ="Net Income "&TEXT(AC46,"0.0")&"B" -> Net Income 387.9B

Sheet Data
B2: Titan Company Ltd (NSE: TITAN): source data & notes
B3: Blue = hard-coded source data. ₹ crore; fiscal years end 31 March (2026 = Apr-2025 to Mar-2026).
B5: HISTORICAL FINANCIALS, CONSOLIDATED (₹ crore)
B6: Fiscal year | C6: Revenue | D6: Net income | E6: Net margin | F6: Revenue growth | G6: NI growth
B7: 2017 | C7: 13382.1 | D7: 711.5 | E7: =IF(C7=0,0,D7/C7) -> 0.053168038
B8: 2018 | C8: 16156 | D8: 1130.1 | E8: =IF(C8=0,0,D8/C8) -> 0.069949245 | F8: =IF(C7=0,0,C8/C7-1) -> 0.20728436 | G8: =IF(D7=0,0,D8/D7-1) -> 0.5883345
B9: 2019 | C9: 19778.5 | D9: 1404.2 | E9: =IF(C9=0,0,D9/C9) -> 0.070996284 | F9: =IF(C8=0,0,C9/C8-1) -> 0.2242201 | G9: =IF(D8=0,0,D9/D8-1) -> 0.24254491
B10: 2020 | C10: 21051.5 | D10: 1501.4 | E10: =IF(C10=0,0,D10/C10) -> 0.071320333 | F10: =IF(C9=0,0,C10/C9-1) -> 0.064362818 | G10: =IF(D9=0,0,D10/D9-1) -> 0.069220909
B11: 2021 | C11: 21644 | D11: 973 | E11: =IF(C11=0,0,D11/C11) -> 0.044954722 | F11: =IF(C10=0,0,C11/C10-1) -> 0.028145263 | G11: =IF(D10=0,0,D11/D10-1) -> -0.35193819
B12: 2022 | C12: 28799 | D12: 2173 | E12: =IF(C12=0,0,D12/C12) -> 0.075454009 | F12: =IF(C11=0,0,C12/C11-1) -> 0.3305766 | G12: =IF(D11=0,0,D12/D11-1) -> 1.2332991
B13: 2023 | C13: 40575 | D13: 3250 | E13: =IF(C13=0,0,D13/C13) -> 0.080098583 | F13: =IF(C12=0,0,C13/C12-1) -> 0.40890309 | G13: =IF(D12=0,0,D13/D12-1) -> 0.49562816
B14: 2024 | C14: 51084 | D14: 3496 | E14: =IF(C14=0,0,D14/C14) -> 0.068436301 | F14: =IF(C13=0,0,C14/C13-1) -> 0.25900185 | G14: =IF(D13=0,0,D14/D13-1) -> 0.075692308
B15: 2025 | C15: 60456 | D15: 3337 | E15: =IF(C15=0,0,D15/C15) -> 0.055197168 | F15: =IF(C14=0,0,C15/C14-1) -> 0.18346253 | G15: =IF(D14=0,0,D15/D14-1) -> -0.045480549
B16: 2026 | C16: 87584 | D16: 5073 | E16: =IF(C16=0,0,D16/C16) -> 0.057921538 | F16: =IF(C15=0,0,C16/C15-1) -> 0.44872304 | G16: =IF(D15=0,0,D16/D15-1) -> 0.52022775
B17: Source: company filings (consolidated), via Alpha Spread and Screener.in, retrieved 26-Sep-2026. Revenue = revenue from operations; net income = profit attributable to shareholders.
B19: LATEST REPORTED QUARTER (₹ crore)
B20: Quarter | C20: Revenue | D20: Net income | E20: Net margin
B21: Q1 FY2027 (Apr–Jun 2026) | C21: 21356 | D21: 1777 | E21: =IF(C21=0,0,D21/C21) -> 0.083208466
B22: Q1 FY2026 (Apr–Jun 2025) | C22: 16523 | D22: 1091 | E22: =IF(C22=0,0,D22/C22) -> 0.066029171
B23: Source: Screener.in quarterly results (consolidated). The FY2027 estimate includes this reported Q1; the model values the stock as of the price date (1-Oct-2026) and counts the remaining 50% of FY2027.
B25: METHODOLOGY
B26: 1. Discounted earnings: each year's net income is treated as the cash flow to equity. Equity value = PV of net income + PV of terminal value + net adjustments (none). This is not a free-cash-flow DCF; see the FCFF DCF sheet.
B27: 2. Revenue: FY2026 actual (₹875.8 bn) grows 17.2%, 17.6% and 17.0% in FY2027–FY2029 (analyst estimates), then fades on an S-curve from 17.04% to 6.95% by FY2042. The fade from FY2030 is my own assumption: it replaces the analysts' 7.2% estimate for FY2030. CAGR FY2026–FY2042: 12.6%.
B28: 3. Net margin: fades on an S-curve (weight 3x² – 2x³, x = t/16) from 6.71% to 6.63% by FY2042.
B29: 4. Timing: valuation date = price date (1-Oct-2026). The remaining 50% of FY2027 net income is counted; cash flows are discounted to each 31-March year-end (0.50, 1.50, … years).
B30: 5. Discount rate: 10.26% cost of equity. Explicit forecast: FY2028–FY2042 (15 years) plus the FY2027 stub.
B31: 6. Terminal value: FY2042 net income × 26.52x exit P/E, discounted with the FY2042 factor.
B32: 7. Value per share: equity value / 890 mn diluted shares = ₹4,057.51, 10.1% below the ₹4,515.70 market price (NSE close, 1-Oct-2026).
B35: SOURCES
B36: Alpha Spread: TITAN DCF base case (forecast assumptions to FY2029, cost of equity, exit multiple), retrieved 26-Sep-2026
B37: Screener.in: Titan Company consolidated financials
... B39: For education and analysis only; not investment advice.
